Workbook

Sheet Cover
B3: Project Northbridge
B5: Buy-side financial due diligence: Transaction Analytics databook
B7: Target: Northbridge Software Ltd
B8: Status: DRAFT for discussion. Subject to management's answers to the Q&A log.
B9: Date: 27 September 2026
B10: Data: data-room extract, January 2022 to December 2025 (six tables).
B12: Synthetic data. This is a self-directed simulation of buy-side financial due diligence on a fictional company, built for a portfolio. It is not client work and uses no real company's data.
B14: Colour convention: blue figures are inputs loaded from the pipeline (outputs/tables/); black figures are Excel formulas.
B15: Units: £'000 unless a column says otherwise. Negative numbers are shown in brackets.

Sheet Contents
A1: Contents
A3: Tab | B3: What it shows
A4: Basis | B4: Data sources, period, definitions, cleaning adjustments and limitations
A5: Reconciliation | B5: Monthly, annual and product-line reconciliation and the source-to-reported walk
A6: 4a Revenue quality | B6: Recurring and one-off revenue, ARR at each year end, headline against normalised growth
A7: 4b Concentration | B7: Top 1/5/10/20 shares, large accounts, declining top customers
A8: 4c Cohorts | B8: Retention at 6, 12 and 18 months by signup year, older against newer cohorts, retention triangles
A9: 4d NRR GRR | B9: NRR and GRR by year with sensitivities (excluding top 5, excluding price) and sourced SMB benchmarks
A10: 4e ARR bridge | B10: ARR bridge December to December and the year-on-year revenue bridge
A11: 4f Margin | B11: Gross margin by line, mix against rate, reconciliation to management gross profit, size bands, discounts
A12: 4g Segments | B12: Revenue, growth, logo churn, NRR and GRR by industry, region, channel and size, with sample sizes
A13: Q&A log | B13: Questions for management raised by Steps 2 to 4
A14: Checks | B14: Every tie-out as a TRUE/FALSE formula, and one overall check

Sheet Basis
A1: Basis of preparation
A2: Units: £'000 unless stated
A3: Source: data room; docs/cleaning_log.md; docs/metric_definitions.md
A5: Data sources | B5: Six CSV tables from the seller's data room: customers, products, subscriptions, invoices, costs and monthly management accounts.
A6: Period | B6: January 2022 to December 2025, monthly. Customer signups and contract start dates go back to 2017.
A7: Revenue basis | B7: Cleaned invoice ledger (the revenue cube). It ties to the management accounts' product lines in all 48 months (Reconciliation tab).
A8: Definitions | B8: All metrics follow docs/metric_definitions.md (link below). Key terms: net revenue = billings plus credit notes; MRR = recurring billings before credit notes; ARR = December MRR × 12.
A9: NRR and GRR | B9: Available for 2023, 2024 and 2025 only: the data has no December 2021 opening point.
A10: Price increases | B10: Every recurring line was billed 5% above its contracted price from January 2024 and a further 7% from January 2025; treated as a price increase (Q15).
A11: Metric definitions | B11: https://github.com/xbhxnxv/northbridge-buyside-diligence/blob/main/docs/metric_definitions.md
A13: Cleaning adjustments: change to net revenue (£'000)
A14: Adjustment | B14: Issue | C14: Table | D14: Action | E14: Records | F14: 2022 | G14: 2023 | H14: 2024 | I14: 2025 | J14: Total | K14: Rule
A15: A01 | B15: P04 | C15: invoices | D15: removed | E15: 40 | F15: -8596.92 | G15: -70158.24 | H15: -7115.7 | I15: -11086.4 | J15: =SUM(F15:I15) -> -96957.26 | K15: Remove exact duplicate invoices. Duplicate key: customer_id, product_id, invoice_date, amount, revenue_type, status. Keep the lowest invoice_id; remove the later copy.
A16: A02 | B16: P06 | C16: invoices | D16: flagged | E16: 15 | F16: 5788.75 | G16: 2118.96 | H16: 4073.48 | I16: 1862.63 | J16: =SUM(F16:I16) -> 13843.82 | K16: Flag negative amounts on invoices marked paid or overdue (anomaly_flag) and carry amount_as_reported, amount_flipped and amount_excluded. Settled in Step 3: the cube uses amount_excluded (cfg_settings.anomaly_treatment = excluded), so these rows contribute zero to revenue and MRR.
A17: A03 | B17: P03 | C17: invoices | D17: linked | E17: 1084 | F17: 0 | G17: 0 | H17: 0 | I17: 0 | J17: =SUM(F17:I17) -> 0 | K17: Keep credit notes as negative revenue in the month they are dated. Link each to the original invoice with the same customer, product, date and absolute amount (credit_note_original_id, credited_by_id).
A18: A04 | B18: P08 | C18: customers | D18: filled | E18: 132 | F18: 0 | G18: 0 | H18: 0 | I18: 0 | J18: =SUM(F18:I18) -> 0 | K18: Set missing industry to Unknown and set industry_missing_flag.
A19: A05 | B19: P07 | C19: customers | D19: flagged | E19: 458 | F19: 0 | G19: 0 | H19: 0 | I19: 0 | J19: =SUM(F19:I19) -> 0 | K19: Set name_collision_flag where another customer_id shares the normalised name key. No ids are merged.
A20: A06 | B20: P11 | C20: customers | D20: standardised | E20: 382 | F20: 0 | G20: 0 | H20: 0 | I20: 0 | J20: =SUM(F20:I20) -> 0 | K20: Build customer_name_std: trim, collapse spaces, strip trailing punctuation, Limited to Ltd, Grp to Group, "and" to "&". The raw customer_name is kept.
A21: A07 | B21: P02 | C21: invoices | D21: categorised | E21: 45 | F21: 0 | G21: 0 | H21: 0 | I21: 0 | J21: =SUM(F21:I21) -> 0 | K21: Set oneoff_category on one-off invoices: signup_implementation when billed in the customer's signup month, other_implementation otherwise.
A22: A08 | B22: P05 | C22: management_accounts | D22: flagged | E22: 4 | F22: 0 | G22: 0 | H22: 0 | I22: 0 | J22: =SUM(F22:I22) -> 0 | K22: Carry revenue_sum_of_lines, lines_less_total and lines_total_mismatch_flag alongside the reported total_revenue.
A23: A09 | B23: P10 | C23: invoices | D23: flagged | E23: 1423 | F23: 0 | G23: 0 | H23: 0 | I23: 0 | J23: =SUM(F23:I23) -> 0 | K23: Set before_signup_flag where invoice_date is earlier than the customer's signup_date. No change to dates.
A24: A10 | B24: P01 | C24: customers | D24: flagged | E24: 6 | F24: 0 | G24: 0 | H24: 0 | I24: 0 | J24: =SUM(F24:I24) -> 0 | K24: Set is_large_account where any subscription line is priced at 10x list price or more.
A25: Total | F25: =SUM(F15:F24) -> -2808.17 | G25: =SUM(G15:G24) -> -68039.28 | H25: =SUM(H15:H24) -> -3042.22 | I25: =SUM(I15:I24) -> -9223.77 | J25: =SUM(J15:J24) -> -83113.44
A27: Check: raw invoice total + adjustments = cube net revenue (all years) | F27: =ABS(SUM(Reconciliation!B67:E67)+SUM(Reconciliation!B70:E70)+J25-SUM(Reconciliation!B71:E71))<0.01 -> TRUE
A29: Limitations
A30: - Synthetic data room; no access to management, contracts, the general ledger or the bank statements.
A31: - Four monthly differences between reported total revenue and the product lines are unexplained (Q07, Q12 to Q14).
A32: - Margin by customer size depends on the cost allocation basis; the data room has no cost-to-serve driver.
A33: - SaaS benchmarks on the 4d tab are survey medians whose definitions differ from ours in places (docs/benchmarks.md).
A34: - Customer lifecycle before 2022 relies on subscription dates; invoices before 2022 are not in the data room.

Sheet Reconciliation
A1: Reconciliation of the revenue cube to the management accounts
A2: Units: £'000 unless stated; differences are cube less reported
A3: Source: outputs/tables/step3_*.csv (sql/04_reconciliation.sql); anomaly treatment: excluded (decision D01)
A5: Monthly revenue reconciliation
A6: Month | B6: Year | C6: Mgmt total revenue | D6: Mgmt sum of lines | E6: Cube net revenue | F6: Difference | G6: Difference % | H6: Difference vs lines | I6: Status | J6: Explanation
A7: 44562 | B7: =YEAR(A7) -> 2022 | C7: 2244374.5 | D7: 2244374.5 | E7: 2244374.5 | F7: =E7-C7 -> 0 | G7: =IF(C7=0,0,F7/C7) -> 0 | H7: =E7-D7 -> 0 | I7: tied
A8: 44593 | B8: =YEAR(A8) -> 2022 | C8: 2213487.9 | D8: 2213487.9 | E8: 2213487.9 | F8: =E8-C8 -> 0 | G8: =IF(C8=0,0,F8/C8) -> 0 | H8: =E8-D8 -> 0 | I8: tied
A9: 44621 | B9: =YEAR(A9) -> 2022 | C9: 2249417.7 | D9: 2249417.7 | E9: 2249417.7 | F9: =E9-C9 -> 0 | G9: =IF(C9=0,0,F9/C9) -> 0 | H9: =E9-D9 -> 0 | I9: explained | J9: Ties once 1 negative paid invoice(s) (INV740991, £702.47 as supplied) are excluded, as management did (A02, Q11).
A10: 44652 | B10: =YEAR(A10) -> 2022 | C10: 2327025.3 | D10: 2327025.3 | E10: 2327025.3 | F10: =E10-C10 -> 0 | G10: =IF(C10=0,0,F10/C10) -> 0 | H10: =E10-D10 -> 0 | I10: explained | J10: Ties once 1 negative paid invoice(s) (INV751844, £1,136.08 as supplied) are excluded, as management did (A02, Q11).
A11: 44682 | B11: =YEAR(A11) -> 2022 | C11: 2326968.6 | D11: 2326968.6 | E11: 2326968.6 | F11: =E11-C11 -> 0 | G11: =IF(C11=0,0,F11/C11) -> 0 | H11: =E11-D11 -> 0 | I11: tied
A12: 44713 | B12: =YEAR(A12) -> 2022 | C12: 2381907.2 | D12: 2381907.2 | E12: 2381907.2 | F12: =E12-C12 -> 0 | G12: =IF(C12=0,0,F12/C12) -> 0 | H12: =E12-D12 -> 0 | I12: tied
A13: 44743 | B13: =YEAR(A13) -> 2022 | C13: 2392021.5 | D13: 2392021.5 | E13: 2392021.5 | F13: =E13-C13 -> 0 | G13: =IF(C13=0,0,F13/C13) -> 0 | H13: =E13-D13 -> 0 | I13: explained | J13: Ties once 1 negative paid invoice(s) (INV717181, £1,030.98 as supplied) are excluded, as management did (A02, Q11).
A14: 44774 | B14: =YEAR(A14) -> 2022 | C14: 2365378.1 | D14: 2365378.1 | E14: 2365378.1 | F14: =E14-C14 -> 0 | G14: =IF(C14=0,0,F14/C14) -> 0 | H14: =E14-D14 -> 0 | I14: tied
A15: 44805 | B15: =YEAR(A15) -> 2022 | C15: 2404716.3 | D15: 2404716.3 | E15: 2404716.3 | F15: =E15-C15 -> 0 | G15: =IF(C15=0,0,F15/C15) -> 0 | H15: =E15-D15 -> 0 | I15: explained | J15: Ties once 1 negative paid invoice(s) (INV722989, £2,919.22 as supplied) are excluded, as management did (A02, Q11).
A16: 44835 | B16: =YEAR(A16) -> 2022 | C16: 2395581.8 | D16: 2395581.8 | E16: 2395581.8 | F16: =E16-C16 -> 0 | G16: =IF(C16=0,0,F16/C16) -> 0 | H16: =E16-D16 -> 0 | I16: tied
A17: 44866 | B17: =YEAR(A17) -> 2022 | C17: 2430858.6 | D17: 2430858.6 | E17: 2430858.6 | F17: =E17-C17 -> 0 | G17: =IF(C17=0,0,F17/C17) -> 0 | H17: =E17-D17 -> 0 | I17: tied
A18: 44896 | B18: =YEAR(A18) -> 2022 | C18: 2500414.2 | D18: 2500414.2 | E18: 2500414.2 | F18: =E18-C18 -> 0 | G18: =IF(C18=0,0,F18/C18) -> 0 | H18: =E18-D18 -> 0 | I18: tied
A19: 44927 | B19: =YEAR(A19) -> 2023 | C19: 2553770.3 | D19: 2553770.3 | E19: 2553770.3 | F19: =E19-C19 -> 0 | G19: =IF(C19=0,0,F19/C19) -> 0 | H19: =E19-D19 -> 0 | I19: explained | J19: Ties once 1 negative paid invoice(s) (INV754430, £550.00 as supplied) are excluded, as management did (A02, Q11).
A20: 44958 | B20: =YEAR(A20) -> 2023 | C20: 2615992 | D20: 2615992 | E20: 2615992 | F20: =E20-C20 -> 0 | G20: =IF(C20=0,0,F20/C20) -> 0 | H20: =E20-D20 -> 0 | I20: tied
A21: 44986 | B21: =YEAR(A21) -> 2023 | C21: 2579603.2 | D21: 2579603.2 | E21: 2579603.2 | F21: =E21-C21 -> 0 | G21: =IF(C21=0,0,F21/C21) -> 0 | H21: =E21-D21 -> 0 | I21: tied
A22: 45017 | B22: =YEAR(A22) -> 2023 | C22: 2597741.7 | D22: 2597741.7 | E22: 2597741.7 | F22: =E22-C22 -> 0 | G22: =IF(C22=0,0,F22/C22) -> 0 | H22: =E22-D22 -> 0 | I22: tied
A23: 45047 | B23: =YEAR(A23) -> 2023 | C23: 2696935.6 | D23: 2696935.6 | E23: 2696935.6 | F23: =E23-C23 -> 0 | G23: =IF(C23=0,0,F23/C23) -> 0 | H23: =E23-D23 -> 0 | I23: tied
A24: 45078 | B24: =YEAR(A24) -> 2023 | C24: 2716929.6 | D24: 2735429.6 | E24: 2735429.6 | F24: =E24-C24 -> 18500 | G24: =IF(C24=0,0,F24/C24) -> 0.0068091569 | H24: =E24-D24 -> 0 | I24: unexplained | J24: Cube ties to the sum of the management product lines. The reported total is £18,500 below the lines, a manual difference not allocated to any product line (Q07, Q12 to Q14).
A25: 45108 | B25: =YEAR(A25) -> 2023 | C25: 2681733.3 | D25: 2681733.3 | E25: 2681733.3 | F25: =E25-C25 -> 0 | G25: =IF(C25=0,0,F25/C25) -> 0 | H25: =E25-D25 -> 0 | I25: explained | J25: Ties once 2 negative paid invoice(s) (INV710858, INV758329, £1,568.96 as supplied) are excluded, as management did (A02, Q11).
A26: 45139 | B26: =YEAR(A26) -> 2023 | C26: 2720774.2 | D26: 2720774.2 | E26: 2720774.2 | F26: =E26-C26 -> 0 | G26: =IF(C26=0,0,F26/C26) -> 0 | H26: =E26-D26 -> 0 | I26: tied
A27: 45170 | B27: =YEAR(A27) -> 2023 | C27: 2699118 | D27: 2699118 | E27: 2699118 | F27: =E27-C27 -> 0 | G27: =IF(C27=0,0,F27/C27) -> 0 | H27: =E27-D27 -> 0 | I27: tied
A28: 45200 | B28: =YEAR(A28) -> 2023 | C28: 2733902.3 | D28: 2733902.3 | E28: 2733902.3 | F28: =E28-C28 -> 0 | G28: =IF(C28=0,0,F28/C28) -> 0 | H28: =E28-D28 -> 0 | I28: tied
A29: 45231 | B29: =YEAR(A29) -> 2023 | C29: 2790949.5 | D29: 2790949.5 | E29: 2790949.5 | F29: =E29-C29 -> 0 | G29: =IF(C29=0,0,F29/C29) -> 0 | H29: =E29-D29 -> 0 | I29: tied
A30: 45261 | B30: =YEAR(A30) -> 2023 | C30: 2786920.3 | D30: 2786920.3 | E30: 2786920.3 | F30: =E30-C30 -> 0 | G30: =IF(C30=0,0,F30/C30) -> 0 | H30: =E30-D30 -> 0 | I30: tied
A31: 45292 | B31: =YEAR(A31) -> 2024 | C31: 2936380.2 | D31: 2936380.2 | E31: 2936380.2 | F31: =E31-C31 -> 0 | G31: =IF(C31=0,0,F31/C31) -> 0 | H31: =E31-D31 -> 0 | I31: tied
A32: 45323 | B32: =YEAR(A32) -> 2024 | C32: 3006142.7 | D32: 3006142.7 | E32: 3006142.7 | F32: =E32-C32 -> 0 | G32: =IF(C32=0,0,F32/C32) -> 0 | H32: =E32-D32 -> 0 | I32: tied
A33: 45352 | B33: =YEAR(A33) -> 2024 | C33: 3051622.7 | D33: 3039622.7 | E33: 3039622.7 | F33: =E33-C33 -> -12000 | G33: =IF(C33=0,0,F33/C33) -> -0.0039323342 | H33: =E33-D33 -> 0 | I33: unexplained | J33: Cube ties to the sum of the management product lines. The reported total is £12,000 above the lines, a manual difference not allocated to any product line (Q07, Q12 to Q14). The month also holds 2 negative paid invoice(s) (INV742515, INV775990), excluded as management did.
A34: 45383 | B34: =YEAR(A34) -> 2024 | C34: 3083644.3 | D34: 3083644.3 | E34: 3083644.3 | F34: =E34-C34 -> 0 | G34: =IF(C34=0,0,F34/C34) -> 0 | H34: =E34-D34 -> 0 | I34: explained | J34: Ties once 2 negative paid invoice(s) (INV749523, INV757592, £1,054.82 as supplied) are excluded, as management did (A02, Q11).
A35: 45413 | B35: =YEAR(A35) -> 2024 | C35: 3078701.3 | D35: 3078701.3 | E35: 3078701.3 | F35: =E35-C35 -> 0 | G35: =IF(C35=0,0,F35/C35) -> 0 | H35: =E35-D35 -> 0 | I35: explained | J35: Ties once 1 negative paid invoice(s) (INV713623, £692.38 as supplied) are excluded, as management did (A02, Q11).
A36: 45444 | B36: =YEAR(A36) -> 2024 | C36: 3217773.8 | D36: 3217773.8 | E36: 3217773.8 | F36: =E36-C36 -> 0 | G36: =IF(C36=0,0,F36/C36) -> 0 | H36: =E36-D36 -> 0 | I36: tied
A37: 45474 | B37: =YEAR(A37) -> 2024 | C37: 3132278.9 | D37: 3132278.9 | E37: 3132278.9 | F37: =E37-C37 -> 0 | G37: =IF(C37=0,0,F37/C37) -> 0 | H37: =E37-D37 -> 0 | I37: tied
A38: 45505 | B38: =YEAR(A38) -> 2024 | C38: 3118389.5 | D38: 3118389.5 | E38: 3118389.5 | F38: =E38-C38 -> 0 | G38: =IF(C38=0,0,F38/C38) -> 0 | H38: =E38-D38 -> 0 | I38: tied
A39: 45536 | B39: =YEAR(A39) -> 2024 | C39: 3118592 | D39: 3118592 | E39: 3118592 | F39: =E39-C39 -> 0 | G39: =IF(C39=0,0,F39/C39) -> 0 | H39: =E39-D39 -> 0 | I39: explained | J39: Ties once 1 negative paid invoice(s) (INV706900, £521.81 as supplied) are excluded, as management did (A02, Q11).
A40: 45566 | B40: =YEAR(A40) -> 2024 | C40: 3167941.4 | D40: 3167941.4 | E40: 3167941.4 | F40: =E40-C40 -> 0 | G40: =IF(C40=0,0,F40/C40) -> 0 | H40: =E40-D40 -> 0 | I40: tied
A41: 45597 | B41: =YEAR(A41) -> 2024 | C41: 3190876.1 | D41: 3200376.1 | E41: 3200376.1 | F41: =E41-C41 -> 9500 | G41: =IF(C41=0,0,F41/C41) -> 0.0029772388 | H41: =E41-D41 -> 0 | I41: unexplained | J41: Cube ties to the sum of the management product lines. The reported total is £9,500 below the lines, a manual difference not allocated to any product line (Q07, Q12 to Q14).
A42: 45627 | B42: =YEAR(A42) -> 2024 | C42: 3159055.6 | D42: 3159055.6 | E42: 3159055.6 | F42: =E42-C42 -> 0 | G42: =IF(C42=0,0,F42/C42) -> 0 | H42: =E42-D42 -> 0 | I42: tied
A43: 45658 | B43: =YEAR(A43) -> 2025 | C43: 3859561.7 | D43: 3859561.7 | E43: 3859561.7 | F43: =E43-C43 -> 0 | G43: =IF(C43=0,0,F43/C43) -> 0 | H43: =E43-D43 -> 0 | I43: tied
A44: 45689 | B44: =YEAR(A44) -> 2025 | C44: 3802073.5 | D44: 3787073.5 | E44: 3787073.5 | F44: =E44-C44 -> -15000 | G44: =IF(C44=0,0,F44/C44) -> -0.0039452156 | H44: =E44-D44 -> 0 | I44: unexplained | J44: Cube ties to the sum of the management product lines. The reported total is £15,000 above the lines, a manual difference not allocated to any product line (Q07, Q12 to Q14).
A45: 45717 | B45: =YEAR(A45) -> 2025 | C45: 3790021 | D45: 3790021 | E45: 3790021 | F45: =E45-C45 -> 0 | G45: =IF(C45=0,0,F45/C45) -> 0 | H45: =E45-D45 -> 0 | I45: tied
A46: 45748 | B46: =YEAR(A46) -> 2025 | C46: 3644256 | D46: 3644256 | E46: 3644256 | F46: =E46-C46 -> 0 | G46: =IF(C46=0,0,F46/C46) -> 0 | H46: =E46-D46 -> 0 | I46: explained | J46: Ties once 1 negative paid invoice(s) (INV732944, £599.63 as supplied) are excluded, as management did (A02, Q11).
A47: 45778 | B47: =YEAR(A47) -> 2025 | C47: 3991404.3 | D47: 3991404.3 | E47: 3991404.3 | F47: =E47-C47 -> 0 | G47: =IF(C47=0,0,F47/C47) -> 0 | H47: =E47-D47 -> 0 | I47: tied
A48: 45809 | B48: =YEAR(A48) -> 2025 | C48: 4286165.5 | D48: 4286165.5 | E48: 4286165.5 | F48: =E48-C48 -> 0 | G48: =IF(C48=0,0,F48/C48) -> 0 | H48: =E48-D48 -> 0 | I48: tied
A49: 45839 | B49: =YEAR(A49) -> 2025 | C49: 3531342.8 | D49: 3531342.8 | E49: 3531342.8 | F49: =E49-C49 -> 0 | G49: =IF(C49=0,0,F49/C49) -> 0 | H49: =E49-D49 -> 0 | I49: tied
A50: 45870 | B50: =YEAR(A50) -> 2025 | C50: 3824036.6 | D50: 3824036.6 | E50: 3824036.6 | F50: =E50-C50 -> 0 | G50: =IF(C50=0,0,F50/C50) -> 0 | H50: =E50-D50 -> 0 | I50: explained | J50: Ties once 1 negative paid invoice(s) (INV759641, £1,263.00 as supplied) are excluded, as management did (A02, Q11).
A51: 45901 | B51: =YEAR(A51) -> 2025 | C51: 3599823.3 | D51: 3599823.3 | E51: 3599823.3 | F51: =E51-C51 -> 0 | G51: =IF(C51=0,0,F51/C51) -> 0 | H51: =E51-D51 -> 0 | I51: tied
A52: 45931 | B52: =YEAR(A52) -> 2025 | C52: 3768098.2 | D52: 3768098.2 | E52: 3768098.2 | F52: =E52-C52 -> 0 | G52: =IF(C52=0,0,F52/C52) -> 0 | H52: =E52-D52 -> 0 | I52: tied
A53: 45962 | B53: =YEAR(A53) -> 2025 | C53: 3833118 | D53: 3833118 | E53: 3833118 | F53: =E53-C53 -> 0 | G53: =IF(C53=0,0,F53/C53) -> 0 | H53: =E53-D53 -> 0 | I53: tied
A54: 45992 | B54: =YEAR(A54) -> 2025 | C54: 3841518.7 | D54: 3841518.7 | E54: 3841518.7 | F54: =E54-C54 -> 0 | G54: =IF(C54=0,0,F54/C54) -> 0 | H54: =E54-D54 -> 0 | I54: tied
A55: Total | C55: =SUM(C7:C54) -> 1.4343934e+08 | D55: =SUM(D7:D54) -> 1.4344034e+08 | E55: =SUM(E7:E54) -> 1.4344034e+08 | F55: =SUM(F7:F54) -> 1000 | H55: =SUM(H7:H54) -> 0 | I55: =ABS(H55)<0.01 -> TRUE
A57: Annual reconciliation
A58: Year | B58: Mgmt total revenue | C58: Cube net revenue | D58: Difference | E58: Difference % | F58: Months unexplained | G58: Unexplained items | H58: Cube net per pipeline | I58: Check
A59: 2022 | B59: =SUMIFS($C$7:$C$54,$B$7:$B$54,A59) -> 28232152 | C59: =SUMIFS($E$7:$E$54,$B$7:$B$54,A59) -> 28232152 | D59: =C59-B59 -> 0 | E59: =IF(B59=0,0,D59/B59) -> 0 | F59: =COUNTIFS($B$7:$B$54,A59,$I$7:$I$54,"unexplained") -> 0 | G59: =SUMIFS($F$7:$F$54,$B$7:$B$54,A59,$I$7:$I$54,"unexplained") -> 0 | H59: 28232152 | I59: =AND(ABS(D59-G59)<0.005,ABS(C59-H59)<0.005) -> TRUE
A60: 2023 | B60: =SUMIFS($C$7:$C$54,$B$7:$B$54,A60) -> 32174370 | C60: =SUMIFS($E$7:$E$54,$B$7:$B$54,A60) -> 32192870 | D60: =C60-B60 -> 18500 | E60: =IF(B60=0,0,D60/B60) -> 0.00057499183 | F60: =COUNTIFS($B$7:$B$54,A60,$I$7:$I$54,"unexplained") -> 1 | G60: =SUMIFS($F$7:$F$54,$B$7:$B$54,A60,$I$7:$I$54,"unexplained") -> 18500 | H60: 32192870 | I60: =AND(ABS(D60-G60)<0.005,ABS(C60-H60)<0.005) -> TRUE
A61: 2024 | B61: =SUMIFS($C$7:$C$54,$B$7:$B$54,A61) -> 37261399 | C61: =SUMIFS($E$7:$E$54,$B$7:$B$54,A61) -> 37258899 | D61: =C61-B61 -> -2500 | E61: =IF(B61=0,0,D61/B61) -> -6.7093563e-05 | F61: =COUNTIFS($B$7:$B$54,A61,$I$7:$I$54,"unexplained") -> 2 | G61: =SUMIFS($F$7:$F$54,$B$7:$B$54,A61,$I$7:$I$54,"unexplained") -> -2500 | H61: 37258899 | I61: =AND(ABS(D61-G61)<0.005,ABS(C61-H61)<0.005) -> TRUE
A62: 2025 | B62: =SUMIFS($C$7:$C$54,$B$7:$B$54,A62) -> 45771419 | C62: =SUMIFS($E$7:$E$54,$B$7:$B$54,A62) -> 45756419 | D62: =C62-B62 -> -15000 | E62: =IF(B62=0,0,D62/B62) -> -0.00032771542 | F62: =COUNTIFS($B$7:$B$54,A62,$I$7:$I$54,"unexplained") -> 1 | G62: =SUMIFS($F$7:$F$54,$B$7:$B$54,A62,$I$7:$I$54,"unexplained") -> -15000 | H62: 45756419 | I62: =AND(ABS(D62-G62)<0.005,ABS(C62-H62)<0.005) -> TRUE
A65: Source-to-reported walk (anomaly treatment: excluded)
A66: £'000 | B66: 2022 | C66: 2023 | D66: 2024 | E66: 2025
A67: Raw gross billings | B67: 28564164 | C67: 32537963 | D67: 37583315 | E67: 46174480
A68: Less duplicates | B68: -8596.92 | C68: -70158.24 | D68: -7115.7 | E68: -11086.4
A69: Anomaly treatment | B69: 5788.75 | C69: 2118.96 | D69: 4073.48 | E69: 1862.63
A70: Credit notes | B70: -329204.58 | C70: -277053.69 | D70: -321374.32 | E70: -408836.48
A71: Cube net revenue | B71: =SUM(B67:B70) -> 28232152 | C71: =SUM(C67:C70) -> 32192870 | D71: =SUM(D67:D70) -> 37258899 | E71: =SUM(E67:E70) -> 45756419
A72: Unreconciled difference | B72: =B73-B71 -> 0 | C72: =C73-C71 -> -18500 | D72: =D73-D71 -> 2500 | E72: =E73-E71 -> 15000
A73: Management total revenue | B73: =B59 -> 28232152 | C73: =B60 -> 32174370 | D73: =B61 -> 37261399 | E73: =B62 -> 45771419
A74: Check: cube net equals annual table | B74: =ABS(B71-C59)<0.005 -> TRUE | C74: =ABS(C71-C60)<0.005 -> TRUE | D74: =ABS(D71-C61)<0.005 -> TRUE | E74: =ABS(E71-C62)<0.005 -> TRUE
A77: Product-line reconciliation (annual)
A78: Product line | B78: Year | C78: Mgmt revenue | D78: Cube net revenue | E78: Difference | F78: Months tied
A79: Analytics Add-on | B79: 2022 | C79: 3078864.2 | D79: 3078864.2 | E79: =D79-C79 -> 0 | F79: 12
A80: Core Platform | B80: 2022 | C80: 20979314 | D80: 20979314 | E80: =D80-C80 -> 0 | F80: 12
A81: Implementation Services | B81: 2022 | C81: 983859.59 | D81: 983859.59 | E81: =D81-C81 -> 0 | F81: 12
A82: Payments Module | B82: 2022 | C82: 3190113.9 | D82: 3190113.9 | E82: =D82-C82 -> 0 | F82: 12
A83: Analytics Add-on | B83: 2023 | C83: 3594489.9 | D83: 3594489.9 | E83: =D83-C83 -> 0 | F83: 12
A84: Core Platform | B84: 2023 | C84: 23830469 | D84: 23830469 | E84: =D84-C84 -> 0 | F84: 12
A85: Implementation Services | B85: 2023 | C85: 1178203.8 | D85: 1178203.8 | E85: =D85-C85 -> 0 | F85: 12
A86: Payments Module | B86: 2023 | C86: 3589707 | D86: 3589707 | E86: =D86-C86 -> 0 | F86: 12
A87: Analytics Add-on | B87: 2024 | C87: 4168383.6 | D87: 4168383.6 | E87: =D87-C87 -> 0 | F87: 12
A88: Core Platform | B88: 2024 | C88: 27735969 | D88: 27735969 | E88: =D88-C88 -> 0 | F88: 12
A89: Implementation Services | B89: 2024 | C89: 1144214.8 | D89: 1144214.8 | E89: =D89-C89 -> 0 | F89: 12
A90: Payments Module | B90: 2024 | C90: 4210331.4 | D90: 4210331.4 | E90: =D90-C90 -> 0 | F90: 12
... A94: Payments Module | B94: 2025 | C94: 4315372.4 | D94: 4315372.4 | E94: =D94-C94 -> 0 | F94: 12
A95: Total | E95: =SUM(E79:E94) -> 0 | F95: =ABS(E95)<0.005 -> TRUE
J98: DRAFT commentary for review (drafted from outputs/key_findings.md): F08 (Low): Revenue is real and reconciles. The cleaned invoice ledger ties to the management accounts' product lines in all 48 months. Reported total revenue carries four unexplained round-number adjustments: the reported total is £18,500 below the invoices in 2023, £2,500 above in 2024 and £15,000 above in 2025. 40 duplicate invoices (£96,957) were removed from the data-room extract, and 15 negative paid invoices suggest reported revenue is understated by £13,844 over four years.

Sheet 4a Revenue quality
A1: 4a. Revenue quality: recurring against one-off, ARR and growth
A2: Units: £'000 unless stated
A3: Source: outputs/tables/4a_revenue_mix.csv, 4a_arr.csv, 4a_uplift_factors.csv (notebooks/04a_revenue_quality.ipynb)
A5: Revenue by type
A6: Year | B6: Recurring | C6: Implementation at signup | D6: Other implementation | E6: One-off | F6: Net revenue | G6: Recurring % | H6: Other impl. % | I6: Headline growth | J6: Recurring growth | K6: Growth ex other impl. | L6: Gap: headline less recurring (pts) | M6: Net revenue per Reconciliation | N6: Check
A7: 2022 | B7: 27248292 | C7: 983859.59 | D7: 0 | E7: =C7+D7 -> 983859.59 | F7: =B7+E7 -> 28232152 | G7: =B7/F7 -> 0.96515109 | H7: =D7/F7 -> 0 | M7: =SUMIFS(Reconciliation!$C$59:$C$62,Reconciliation!$A$59:$A$62,A7) -> 28232152 | N7: =ABS(F7-M7)<0.005 -> TRUE
A8: 2023 | B8: 31014666 | C8: 1178203.8 | D8: 0 | E8: =C8+D8 -> 1178203.8 | F8: =B8+E8 -> 32192870 | G8: =B8/F8 -> 0.96340172 | H8: =D8/F8 -> 0 | I8: =F8/F7-1 -> 0.14029105 | J8: =B8/B7-1 -> 0.13822423 | K8: =(F8-D8)/(F7-D7)-1 -> 0.14029105 | L8: =(I8-J8)*100 -> 0.20668272 | M8: =SUMIFS(Reconciliation!$C$59:$C$62,Reconciliation!$A$59:$A$62,A8) -> 32192870 | N8: =ABS(F8-M8)<0.005 -> TRUE
A9: 2024 | B9: 36114684 | C9: 1144214.8 | D9: 0 | E9: =C9+D9 -> 1144214.8 | F9: =B9+E9 -> 37258899 | G9: =B9/F9 -> 0.96929016 | H9: =D9/F9 -> 0 | I9: =F9/F8-1 -> 0.15736492 | J9: =B9/B8-1 -> 0.1644389 | K9: =(F9-D9)/(F8-D8)-1 -> 0.15736492 | L9: =(I9-J9)*100 -> -0.70739737 | M9: =SUMIFS(Reconciliation!$C$59:$C$62,Reconciliation!$A$59:$A$62,A9) -> 37258899 | N9: =ABS(F9-M9)<0.005 -> TRUE
A10: 2025 | B10: 40475097 | C10: 1204747.9 | D10: 4076574.3 | E10: =C10+D10 -> 5281322.2 | F10: =B10+E10 -> 45756419 | G10: =B10/F10 -> 0.88457746 | H10: =D10/F10 -> 0.089092948 | I10: =F10/F9-1 -> 0.22806688 | J10: =B10/B9-1 -> 0.12073797 | K10: =(F10-D10)/(F9-D9)-1 -> 0.11865478 | L10: =(I10-J10)*100 -> 10.732892 | M10: =SUMIFS(Reconciliation!$C$59:$C$62,Reconciliation!$A$59:$A$62,A10) -> 45756419 | N10: =ABS(F10-M10)<0.005 -> TRUE
A13: ARR at each year end (December MRR × 12)
A14: Year | B14: ARR | C14: Active customers | D14: ARR per customer (£) | E14: Uplift factor k | F14: ARR growth | G14: ARR growth before price increase
A15: 2022 | B15: 29005684 | C15: 1010 | D15: =B15/C15 -> 28718.499 | E15: 1
A16: 2023 | B16: 32781343 | C16: 1205 | D16: =B16/C16 -> 27204.434 | E16: 1 | F16: =B16/B15-1 -> 0.13016963 | G16: =(B16/E16)/B15-1 -> 0.13016963
A17: 2024 | B17: 37496836 | C17: 1343 | D17: =B17/C17 -> 27920.206 | E17: 1.05 | F17: =B17/B16-1 -> 0.14384687 | G17: =(B17/E17)/B16-1 -> 0.08937797
A18: 2025 | B18: 41359828 | C18: 1462 | D18: =B18/C18 -> 28289.896 | E18: 1.07 | F18: =B18/B17-1 -> 0.10302181 | G18: =(B18/E18)/B17-1 -> 0.030861501
L21: DRAFT commentary for review (drafted from outputs/key_findings.md): F01 (High): One-off revenue flatters 2025 growth. Headline revenue growth is 22.8%; recurring revenue grew 12.1% and revenue excluding the 45 'other implementation' invoices billed in 2025 grew 11.9%. Those invoices total £4.08m (8.9% of 2025 revenue), all to existing customers, none in the customer's signup month. Recurring share fell from 96.9% in 2024 to 88.5%.

Sheet 4b Concentration
A1: 4b. Customer concentration
A2: Units: £'000 unless stated
A3: Source: outputs/tables/4b_*.csv (notebooks/04b_concentration.ipynb)
A5: Share of net revenue and of recurring revenue held by the largest customers
A6: Year | B6: Top N | C6: Top-N net revenue | D6: Total net revenue | E6: Share of net | F6: Top-N recurring | G6: Total recurring | H6: Share of recurring | I6: Total per 4a | J6: Check
A7: 2022 | B7: 1 | C7: 2167499.9 | D7: 28232152 | E7: =C7/D7 -> 0.076774167 | F7: 2167499.9 | G7: 27248292 | H7: =F7/G7 -> 0.079546267 | I7: =SUMIFS('4a Revenue quality'!$F$7:$F$10,'4a Revenue quality'!$A$7:$A$10,A7) -> 28232152 | J7: =AND(ABS(D7-I7)<0.005,E7>0,E7<=1) -> TRUE
A8: 2022 | B8: 5 | C8: 8408750 | D8: 28232152 | E8: =C8/D8 -> 0.29784305 | F8: 8408750 | G8: 27248292 | H8: =F8/G8 -> 0.30859733 | I8: =SUMIFS('4a Revenue quality'!$F$7:$F$10,'4a Revenue quality'!$A$7:$A$10,A8) -> 28232152 | J8: =AND(ABS(D8-I8)<0.005,E8>0,E8<=1) -> TRUE
A9: 2022 | B9: 10 | C9: 9436266.6 | D9: 28232152 | E9: =C9/D9 -> 0.33423831 | F9: 9436266.6 | G9: 27248292 | H9: =F9/G9 -> 0.34630672 | I9: =SUMIFS('4a Revenue quality'!$F$7:$F$10,'4a Revenue quality'!$A$7:$A$10,A9) -> 28232152 | J9: =AND(ABS(D9-I9)<0.005,E9>0,E9<=1) -> TRUE
A10: 2022 | B10: 20 | C10: 9891498.7 | D10: 28232152 | E10: =C10/D10 -> 0.35036291 | F10: 9891498.7 | G10: 27248292 | H10: =F10/G10 -> 0.36301353 | I10: =SUMIFS('4a Revenue quality'!$F$7:$F$10,'4a Revenue quality'!$A$7:$A$10,A10) -> 28232152 | J10: =AND(ABS(D10-I10)<0.005,E10>0,E10<=1) -> TRUE
A11: 2023 | B11: 1 | C11: 2209999.9 | D11: 32192870 | E11: =C11/D11 -> 0.068648739 | F11: 2209999.9 | G11: 31014666 | H11: =F11/G11 -> 0.071256608 | I11: =SUMIFS('4a Revenue quality'!$F$7:$F$10,'4a Revenue quality'!$A$7:$A$10,A11) -> 32192870 | J11: =AND(ABS(D11-I11)<0.005,E11>0,E11<=1) -> TRUE
A12: 2023 | B12: 5 | C12: 8465000 | D12: 32192870 | E12: =C12/D12 -> 0.26294642 | F12: 8465000 | G12: 31014666 | H12: =F12/G12 -> 0.27293539 | I12: =SUMIFS('4a Revenue quality'!$F$7:$F$10,'4a Revenue quality'!$A$7:$A$10,A12) -> 32192870 | J12: =AND(ABS(D12-I12)<0.005,E12>0,E12<=1) -> TRUE
A13: 2023 | B13: 10 | C13: 9580880.5 | D13: 32192870 | E13: =C13/D13 -> 0.29760877 | F13: 9561310.1 | G13: 31014666 | H13: =F13/G13 -> 0.30828351 | I13: =SUMIFS('4a Revenue quality'!$F$7:$F$10,'4a Revenue quality'!$A$7:$A$10,A13) -> 32192870 | J13: =AND(ABS(D13-I13)<0.005,E13>0,E13<=1) -> TRUE
A14: 2023 | B14: 20 | C14: 10048875 | D14: 32192870 | E14: =C14/D14 -> 0.31214598 | F14: 10020725 | G14: 31014666 | H14: =F14/G14 -> 0.32309633 | I14: =SUMIFS('4a Revenue quality'!$F$7:$F$10,'4a Revenue quality'!$A$7:$A$10,A14) -> 32192870 | J14: =AND(ABS(D14-I14)<0.005,E14>0,E14<=1) -> TRUE
A15: 2024 | B15: 1 | C15: 2320499.9 | D15: 37258899 | E15: =C15/D15 -> 0.062280421 | F15: 2320499.9 | G15: 36114684 | H15: =F15/G15 -> 0.06425364 | I15: =SUMIFS('4a Revenue quality'!$F$7:$F$10,'4a Revenue quality'!$A$7:$A$10,A15) -> 37258899 | J15: =AND(ABS(D15-I15)<0.005,E15>0,E15<=1) -> TRUE
A16: 2024 | B16: 5 | C16: 8777999.9 | D16: 37258899 | E16: =C16/D16 -> 0.23559472 | F16: 8777999.9 | G16: 36114684 | H16: =F16/G16 -> 0.24305903 | I16: =SUMIFS('4a Revenue quality'!$F$7:$F$10,'4a Revenue quality'!$A$7:$A$10,A16) -> 37258899 | J16: =AND(ABS(D16-I16)<0.005,E16>0,E16<=1) -> TRUE
A17: 2024 | B17: 10 | C17: 9930371.3 | D17: 37258899 | E17: =C17/D17 -> 0.26652348 | F17: 9930371.3 | G17: 36114684 | H17: =F17/G17 -> 0.27496769 | I17: =SUMIFS('4a Revenue quality'!$F$7:$F$10,'4a Revenue quality'!$A$7:$A$10,A17) -> 37258899 | J17: =AND(ABS(D17-I17)<0.005,E17>0,E17<=1) -> TRUE
A18: 2024 | B18: 20 | C18: 10423582 | D18: 37258899 | E18: =C18/D18 -> 0.27976087 | F18: 10423080 | G18: 36114684 | H18: =F18/G18 -> 0.28861058 | I18: =SUMIFS('4a Revenue quality'!$F$7:$F$10,'4a Revenue quality'!$A$7:$A$10,A18) -> 37258899 | J18: =AND(ABS(D18-I18)<0.005,E18>0,E18<=1) -> TRUE
... A22: 2025 | B22: 20 | C22: 11683512 | D22: 45756419 | E22: =C22/D22 -> 0.25534149 | F22: 10285384 | G22: 40475097 | H22: =F22/G22 -> 0.25411636 | I22: =SUMIFS('4a Revenue quality'!$F$7:$F$10,'4a Revenue quality'!$A$7:$A$10,A22) -> 45756419 | J22: =AND(ABS(D22-I22)<0.005,E22>0,E22<=1) -> TRUE
A24: Share of net revenue by year (for the chart) | M24: DRAFT commentary for review (drafted from outputs/key_findings.md): F05 (High): Six large accounts carry 20.8% of 2025 revenue (32.7% in 2022), and two of them are shrinking. C1052's December ARR fell £983,535 (down 42.4%) to £1.34m after it dropped Analytics Add-on (ended 2025-09-01) and Payments Module (ended 2025-09-01). C1545's December ARR fell £243,915 (down 11.9%) to £1.81m after it dropped Payments Module (ended 2025-02-01). The largest customer was 4.6% of 2025 revenue; no customer exceeded 10% in any year.
A25: Year | B25: Top 1 | C25: Top 5 | D25: Top 10 | E25: Top 20
A26: 2022 | B26: =SUMIFS($E$7:$E$22,$A$7:$A$22,2022,$B$7:$B$22,1) -> 0.076774167 | C26: =SUMIFS($E$7:$E$22,$A$7:$A$22,2022,$B$7:$B$22,5) -> 0.29784305 | D26: =SUMIFS($E$7:$E$22,$A$7:$A$22,2022,$B$7:$B$22,10) -> 0.33423831 | E26: =SUMIFS($E$7:$E$22,$A$7:$A$22,2022,$B$7:$B$22,20) -> 0.35036291
A27: 2023 | B27: =SUMIFS($E$7:$E$22,$A$7:$A$22,2023,$B$7:$B$22,1) -> 0.068648739 | C27: =SUMIFS($E$7:$E$22,$A$7:$A$22,2023,$B$7:$B$22,5) -> 0.26294642 | D27: =SUMIFS($E$7:$E$22,$A$7:$A$22,2023,$B$7:$B$22,10) -> 0.29760877 | E27: =SUMIFS($E$7:$E$22,$A$7:$A$22,2023,$B$7:$B$22,20) -> 0.31214598
A28: 2024 | B28: =SUMIFS($E$7:$E$22,$A$7:$A$22,2024,$B$7:$B$22,1) -> 0.062280421 | C28: =SUMIFS($E$7:$E$22,$A$7:$A$22,2024,$B$7:$B$22,5) -> 0.23559472 | D28: =SUMIFS($E$7:$E$22,$A$7:$A$22,2024,$B$7:$B$22,10) -> 0.26652348 | E28: =SUMIFS($E$7:$E$22,$A$7:$A$22,2024,$B$7:$B$22,20) -> 0.27976087
A29: 2025 | B29: =SUMIFS($E$7:$E$22,$A$7:$A$22,2025,$B$7:$B$22,1) -> 0.04591585 | C29: =SUMIFS($E$7:$E$22,$A$7:$A$22,2025,$B$7:$B$22,5) -> 0.18624157 | D29: =SUMIFS($E$7:$E$22,$A$7:$A$22,2025,$B$7:$B$22,10) -> 0.22338647 | E29: =SUMIFS($E$7:$E$22,$A$7:$A$22,2025,$B$7:$B$22,20) -> 0.25534149
A31: Six large accounts (subscription lines priced at 10x list or more)
A32: Year | B32: Large accounts' net revenue | C32: Total net revenue | D32: Share
A33: 2022 | B33: 9245000 | C33: 28232152 | D33: =B33/C33 -> 0.32746353
A34: 2023 | B34: 9365000 | C34: 32192870 | D34: =B34/C34 -> 0.29090293
A35: 2024 | B35: 9722999.9 | C35: 37258899 | D35: =B35/C35 -> 0.26095779
A36: 2025 | B36: 9532897.6 | C36: 45756419 | D36: =B36/C36 -> 0.20834011
A38: Top 10 customers by 2025 net revenue: run-rate (ARR = December MRR × 12)
A39: Rank | B39: Customer | C39: Dec 2024 ARR | D39: Dec 2025 ARR | E39: Change | F39: Change % | G39: Peak ARR | H39: Change vs peak | I39: % vs peak | J39: Declining
A40: 1 | B40: C1052 | C40: 2320499.9 | D40: 1336964.9 | E40: =D40-C40 -> -983535 | F40: =IF(C40=0,0,E40/C40) -> -0.42384618 | G40: 2482934.9 | H40: =D40-G40 -> -1145970 | I40: =IF(G40=0,0,H40/G40) -> -0.46153848 | J40: =IF(E40<0,"yes","no") -> yes
A41: 2 | B41: C1865 | C41: 1890000 | D41: 2022300 | E41: =D41-C41 -> 132300 | F41: =IF(C41=0,0,E41/C41) -> 0.07 | G41: 2022300 | H41: =D41-G41 -> 0 | I41: =IF(G41=0,0,H41/G41) -> 0 | J41: =IF(E41<0,"yes","no") -> no
A42: 3 | B42: C1545 | C42: 2052750 | D42: 1808835 | E42: =D42-C42 -> -243915 | F42: =IF(C42=0,0,E42/C42) -> -0.11882353 | G42: 2196442.6 | H42: =D42-G42 -> -387607.56 | I42: =IF(G42=0,0,H42/G42) -> -0.17647061 | J42: =IF(E42<0,"yes","no") -> yes
A43: 4 | B43: C1881 | C43: 1249500 | D43: 1336965 | E43: =D43-C43 -> 87465 | F43: =IF(C43=0,0,E43/C43) -> 0.07 | G43: 1470000 | H43: =D43-G43 -> -133035 | I43: =IF(G43=0,0,H43/G43) -> -0.0905 | J43: =IF(E43<0,"yes","no") -> no
A44: 5 | B44: C1328 | C44: 1155000 | D44: 1235850.1 | E44: =D44-C44 -> 80850.12 | F44: =IF(C44=0,0,E44/C44) -> 0.070000104 | G44: 1235850.1 | H44: =D44-G44 -> 0 | I44: =IF(G44=0,0,H44/G44) -> 0 | J44: =IF(E44<0,"yes","no") -> no
A45: 6 | B45: C1933 | C45: 945000 | D45: 1011150.1 | E45: =D45-C45 -> 66150.12 | F45: =IF(C45=0,0,E45/C45) -> 0.070000127 | G45: 1011150.1 | H45: =D45-G45 -> 0 | I45: =IF(G45=0,0,H45/G45) -> 0 | J45: =IF(E45<0,"yes","no") -> no
A46: 7 | B46: C1069 | C46: 42607.2 | D46: 45589.68 | E46: =D46-C46 -> 2982.48 | F46: =IF(C46=0,0,E46/C46) -> 0.069999437 | G46: 45589.68 | H46: =D46-G46 -> 0 | I46: =IF(G46=0,0,H46/G46) -> 0 | J46: =IF(E46<0,"yes","no") -> no
A47: 8 | B47: C2470 | C47: 42053.64 | D47: 44997.36 | E47: =D47-C47 -> 2943.72 | F47: =IF(C47=0,0,E47/C47) -> 0.069999172 | G47: 44997.36 | H47: =D47-G47 -> 0 | I47: =IF(G47=0,0,H47/G47) -> 0 | J47: =IF(E47<0,"yes","no") -> no
A48: 9 | B48: C2321 | C48: 42140.52 | D48: 45090.36 | E48: =D48-C48 -> 2949.84 | F48: =IF(C48=0,0,E48/C48) -> 0.070000085 | G48: 45090.36 | H48: =D48-G48 -> 0 | I48: =IF(G48=0,0,H48/G48) -> 0 | J48: =IF(E48<0,"yes","no") -> no
A49: 10 | B49: C1964 | C49: 23562 | D49: 25211.4 | E49: =D49-C49 -> 1649.4 | F49: =IF(C49=0,0,E49/C49) -> 0.070002546 | G49: 25211.4 | H49: =D49-G49 -> 0 | I49: =IF(G49=0,0,H49/G49) -> 0 | J49: =IF(E49<0,"yes","no") -> no

Sheet 4c Cohorts
A1: 4c. Cohorts and retention (tenure-matched)
A2: Units: % of customers or of month-3 MRR
A3: Source: outputs/tables/4c_*.csv (notebooks/04c_cohorts.ipynb). Logo retention from subscription dates; revenue retention from invoiced MRR, cohorts from 2022Q1
A5: Logo retention at the same tenure, by signup year
A6: Signup year | B6: Customers (6m) | C6: Active at 6m | D6: Retention 6m | E6: Customers (12m) | F6: Active at 12m | G6: Retention 12m | H6: Customers (18m) | I6: Active at 18m | J6: Retention 18m
A7: 2017 | B7: 171 | C7: 167 | D7: =C7/B7 -> 0.97660819 | E7: 171 | F7: 160 | G7: =F7/E7 -> 0.93567251 | H7: 171 | I7: 152 | J7: =I7/H7 -> 0.88888889
A8: 2018 | B8: 188 | C8: 185 | D8: =C8/B8 -> 0.98404255 | E8: 188 | F8: 180 | G8: =F8/E8 -> 0.95744681 | H8: 188 | I8: 174 | J8: =I8/H8 -> 0.92553191
A9: 2019 | B9: 205 | C9: 199 | D9: =C9/B9 -> 0.97073171 | E9: 205 | F9: 189 | G9: =F9/E9 -> 0.92195122 | H9: 205 | I9: 180 | J9: =I9/H9 -> 0.87804878
A10: 2020 | B10: 218 | C10: 209 | D10: =C10/B10 -> 0.9587156 | E10: 218 | F10: 202 | G10: =F10/E10 -> 0.9266055 | H10: 218 | I10: 194 | J10: =I10/H10 -> 0.88990826
A11: 2021 | B11: 235 | C11: 228 | D11: =C11/B11 -> 0.97021277 | E11: 235 | F11: 212 | G11: =F11/E11 -> 0.90212766 | H11: 235 | I11: 202 | J11: =I11/H11 -> 0.85957447
A12: 2022 | B12: 242 | C12: 233 | D12: =C12/B12 -> 0.96280992 | E12: 242 | F12: 222 | G12: =F12/E12 -> 0.91735537 | H12: 242 | I12: 208 | J12: =I12/H12 -> 0.85950413
A13: 2023 | B13: 310 | C13: 292 | D13: =C13/B13 -> 0.94193548 | E13: 310 | F13: 256 | G13: =F13/E13 -> 0.82580645 | H13: 310 | I13: 233 | J13: =I13/H13 -> 0.7516129
A14: 2024 | B14: 303 | C14: 273 | D14: =C14/B14 -> 0.9009901 | E14: 303 | F14: 226 | G14: =F14/E14 -> 0.74587459 | J14: n/a
A16: Older (2017-2022) against newer (2023+) signups at the same tenure
A17: Group | B17: Tenure (months) | C17: Customers reaching tenure | D17: Still subscribed | E17: Retention
A18: 2017-2022 signups | B18: 6 | C18: 1259 | D18: 1221 | E18: =D18/C18 -> 0.96981732
A19: 2023+ signups | B19: 6 | C19: 761 | D19: 692 | E19: =D19/C19 -> 0.90932983
A20: 2017-2022 signups | B20: 12 | C20: 1259 | D20: 1165 | E20: =D20/C20 -> 0.92533757
A21: 2023+ signups | B21: 12 | C21: 613 | D21: 482 | E21: =D21/C21 -> 0.7862969
A22: 2017-2022 signups | B22: 18 | C22: 1259 | D22: 1110 | E22: =D22/C22 -> 0.8816521
A23: 2023+ signups | B23: 18 | C23: 474 | D23: 344 | E23: =D23/C23 -> 0.7257384
L24: DRAFT commentary for review (drafted from outputs/key_findings.md): F04 (High): Newer customers leave faster. At the same tenure, 78.6% of customers who signed up from 2023 were still subscribed after 12 months, against 92.5% for 2017 to 2022 signups (74.6% for the 2024 cohort). The fall appears in every channel, size band and industry; it is largest for Micro customers (91.3% to 66.1%).
A41: Logo retention triangle: share of each signup quarter still subscribed, by months since signup (0 to 36)
A42: Signup quarter | B42: 0 | C42: 1 | D42: 2 | E42: 3 | F42: 4 | G42: 5 | H42: 6 | I42: 7 | J42: 8 | K42: 9 | L42: 10 | M42: 11 | N42: 12 | O42: 13 | P42: 14 | Q42: 15 | R42: 16 | S42: 17 | T42: 18 | U42: 19 | V42: 20 | W42: 21 | X42: 22 | Y42: 23 | Z42: 24 | AA42: 25 | AB42: 26 | AC42: 27 | AD42: 28 | AE42: 29 | AF42: 30 | AG42: 31 | AH42: 32 | AI42: 33 | AJ42: 34 | AK42: 35 | AL42: 36
A43: 2017Q1 | B43: 1 | C43: 1 | D43: 1 | E43: 1 | F43: 1 | G43: 1 | H43: 1 | I43: 1 | J43: 1 | K43: 1 | L43: 1 | M43: 0.96666667 | N43: 0.95 | O43: 0.91666667 | P43: 0.91666667 | Q43: 0.9 | R43: 0.88333333 | S43: 0.85 | T43: 0.83333333 | U43: 0.81666667 | V43: 0.8 | W43: 0.8 | X43: 0.8 | Y43: 0.8 | Z43: 0.78333333 | AA43: 0.76666667 | AB43: 0.76666667 | AC43: 0.76666667 | AD43: 0.76666667 | AE43: 0.76666667 | AF43: 0.76666667 | AG43: 0.76666667 | AH43: 0.76666667 | AI43: 0.75 | AJ43: 0.75 | AK43: 0.75 | AL43: 0.73333333
A44: 2017Q2 | B44: 1 | C44: 1 | D44: 1 | E44: 1 | F44: 1 | G44: 0.96875 | H44: 0.9375 | I44: 0.90625 | J44: 0.90625 | K44: 0.90625 | L44: 0.90625 | M44: 0.90625 | N44: 0.90625 | O44: 0.90625 | P44: 0.90625 | Q44: 0.90625 | R44: 0.90625 | S44: 0.90625 | T44: 0.90625 | U44: 0.90625 | V44: 0.875 | W44: 0.84375 | X44: 0.8125 | Y44: 0.8125 | Z44: 0.8125 | AA44: 0.8125 | AB44: 0.8125 | AC44: 0.8125 | AD44: 0.8125 | AE44: 0.8125 | AF44: 0.8125 | AG44: 0.8125 | AH44: 0.8125 | AI44: 0.8125 | AJ44: 0.8125 | AK44: 0.8125 | AL44: 0.8125
A45: 2017Q3 | B45: 1 | C45: 1 | D45: 1 | E45: 1 | F45: 1 | G45: 1 | H45: 1 | I45: 1 | J45: 1 | K45: 0.97222222 | L45: 0.97222222 | M45: 0.94444444 | N45: 0.94444444 | O45: 0.94444444 | P45: 0.94444444 | Q45: 0.91666667 | R45: 0.91666667 | S45: 0.91666667 | T45: 0.91666667 | U45: 0.91666667 | V45: 0.91666667 | W45: 0.91666667 | X45: 0.91666667 | Y45: 0.91666667 | Z45: 0.91666667 | AA45: 0.91666667 | AB45: 0.91666667 | AC45: 0.88888889 | AD45: 0.88888889 | AE45: 0.88888889 | AF45: 0.88888889 | AG45: 0.88888889 | AH45: 0.88888889 | AI45: 0.88888889 | AJ45: 0.88888889 | AK45: 0.88888889 | AL45: 0.88888889
A46: 2017Q4 | B46: 1 | C46: 1 | D46: 1 | E46: 1 | F46: 0.95348837 | G46: 0.95348837 | H46: 0.95348837 | I46: 0.95348837 | J46: 0.93023256 | K46: 0.93023256 | L46: 0.93023256 | M46: 0.93023256 | N46: 0.93023256 | O46: 0.93023256 | P46: 0.93023256 | Q46: 0.93023256 | R46: 0.93023256 | S46: 0.93023256 | T46: 0.93023256 | U46: 0.93023256 | V46: 0.93023256 | W46: 0.93023256 | X46: 0.93023256 | Y46: 0.90697674 | Z46: 0.90697674 | AA46: 0.90697674 | AB46: 0.90697674 | AC46: 0.90697674 | AD46: 0.90697674 | AE46: 0.90697674 | AF46: 0.90697674 | AG46: 0.90697674 | AH46: 0.90697674 | AI46: 0.90697674 | AJ46: 0.86046512 | AK46: 0.86046512 | AL46: 0.86046512
A47: 2018Q1 | B47: 1 | C47: 1 | D47: 1 | E47: 1 | F47: 1 | G47: 1 | H47: 1 | I47: 1 | J47: 1 | K47: 1 | L47: 1 | M47: 0.98 | N47: 0.98 | O47: 0.94 | P47: 0.94 | Q47: 0.92 | R47: 0.92 | S47: 0.9 | T47: 0.9 | U47: 0.9 | V47: 0.9 | W47: 0.9 | X47: 0.9 | Y47: 0.88 | Z47: 0.88 | AA47: 0.88 | AB47: 0.86 | AC47: 0.86 | AD47: 0.84 | AE47: 0.84 | AF47: 0.84 | AG47: 0.84 | AH47: 0.82 | AI47: 0.82 | AJ47: 0.82 | AK47: 0.82 | AL47: 0.82
A48: 2018Q2 | B48: 1 | C48: 1 | D48: 1 | E48: 1 | F48: 1 | G48: 0.97368421 | H48: 0.97368421 | I48: 0.94736842 | J48: 0.94736842 | K48: 0.94736842 | L48: 0.94736842 | M48: 0.94736842 | N48: 0.94736842 | O48: 0.94736842 | P48: 0.94736842 | Q48: 0.94736842 | R48: 0.94736842 | S48: 0.92105263 | T48: 0.92105263 | U48: 0.92105263 | V48: 0.89473684 | W48: 0.89473684 | X48: 0.89473684 | Y48: 0.89473684 | Z48: 0.89473684 | AA48: 0.89473684 | AB48: 0.86842105 | AC48: 0.86842105 | AD48: 0.86842105 | AE48: 0.84210526 | AF48: 0.81578947 | AG48: 0.81578947 | AH48: 0.81578947 | AI48: 0.81578947 | AJ48: 0.81578947 | AK48: 0.81578947 | AL48: 0.81578947
A49: 2018Q3 | B49: 1 | C49: 0.97560976 | D49: 0.97560976 | E49: 0.97560976 | F49: 0.95121951 | G49: 0.95121951 | H49: 0.95121951 | I49: 0.95121951 | J49: 0.92682927 | K49: 0.92682927 | L49: 0.90243902 | M49: 0.90243902 | N49: 0.90243902 | O49: 0.90243902 | P49: 0.90243902 | Q49: 0.90243902 | R49: 0.90243902 | S49: 0.90243902 | T49: 0.90243902 | U49: 0.90243902 | V49: 0.90243902 | W49: 0.90243902 | X49: 0.90243902 | Y49: 0.90243902 | Z49: 0.90243902 | AA49: 0.87804878 | AB49: 0.87804878 | AC49: 0.87804878 | AD49: 0.87804878 | AE49: 0.85365854 | AF49: 0.82926829 | AG49: 0.82926829 | AH49: 0.82926829 | AI49: 0.82926829 | AJ49: 0.82926829 | AK49: 0.82926829 | AL49: 0.82926829
A50: 2018Q4 | B50: 1 | C50: 1 | D50: 1 | E50: 1 | F50: 1 | G50: 1 | H50: 1 | I50: 1 | J50: 1 | K50: 1 | L50: 1 | M50: 1 | N50: 0.98305085 | O50: 0.96610169 | P50: 0.96610169 | Q50: 0.96610169 | R50: 0.96610169 | S50: 0.96610169 | T50: 0.96610169 | U50: 0.94915254 | V50: 0.94915254 | W50: 0.93220339 | X50: 0.93220339 | Y50: 0.93220339 | Z50: 0.93220339 | AA50: 0.93220339 | AB50: 0.91525424 | AC50: 0.89830508 | AD50: 0.89830508 | AE50: 0.89830508 | AF50: 0.89830508 | AG50: 0.89830508 | AH50: 0.86440678 | AI50: 0.86440678 | AJ50: 0.86440678 | AK50: 0.84745763 | AL50: 0.84745763
A51: 2019Q1 | B51: 1 | C51: 1 | D51: 1 | E51: 1 | F51: 1 | G51: 0.94827586 | H51: 0.94827586 | I51: 0.93103448 | J51: 0.93103448 | K51: 0.9137931 | L51: 0.89655172 | M51: 0.87931034 | N51: 0.87931034 | O51: 0.87931034 | P51: 0.87931034 | Q51: 0.86206897 | R51: 0.86206897 | S51: 0.82758621 | T51: 0.82758621 | U51: 0.79310345 | V51: 0.79310345 | W51: 0.77586207 | X51: 0.75862069 | Y51: 0.75862069 | Z51: 0.74137931 | AA51: 0.74137931 | AB51: 0.72413793 | AC51: 0.70689655 | AD51: 0.68965517 | AE51: 0.68965517 | AF51: 0.68965517 | AG51: 0.67241379 | AH51: 0.67241379 | AI51: 0.67241379 | AJ51: 0.67241379 | AK51: 0.67241379 | AL51: 0.67241379
A52: 2019Q2 | B52: 1 | C52: 1 | D52: 1 | E52: 1 | F52: 1 | G52: 1 | H52: 1 | I52: 1 | J52: 0.98076923 | K52: 0.96153846 | L52: 0.96153846 | M52: 0.92307692 | N52: 0.92307692 | O52: 0.92307692 | P52: 0.90384615 | Q52: 0.90384615 | R52: 0.86538462 | S52: 0.86538462 | T52: 0.86538462 | U52: 0.84615385 | V52: 0.84615385 | W52: 0.84615385 | X52: 0.84615385 | Y52: 0.82692308 | Z52: 0.82692308 | AA52: 0.82692308 | AB52: 0.82692308 | AC52: 0.82692308 | AD52: 0.80769231 | AE52: 0.80769231 | AF52: 0.80769231 | AG52: 0.80769231 | AH52: 0.80769231 | AI52: 0.80769231 | AJ52: 0.80769231 | AK52: 0.80769231 | AL52: 0.80769231
A53: 2019Q3 | B53: 1 | C53: 1 | D53: 1 | E53: 1 | F53: 0.97674419 | G53: 0.97674419 | H53: 0.97674419 | I53: 0.97674419 | J53: 0.97674419 | K53: 0.95348837 | L53: 0.95348837 | M53: 0.95348837 | N53: 0.95348837 | O53: 0.95348837 | P53: 0.95348837 | Q53: 0.95348837 | R53: 0.95348837 | S53: 0.95348837 | T53: 0.95348837 | U53: 0.95348837 | V53: 0.95348837 | W53: 0.95348837 | X53: 0.95348837 | Y53: 0.95348837 | Z53: 0.95348837 | AA53: 0.95348837 | AB53: 0.95348837 | AC53: 0.95348837 | AD53: 0.90697674 | AE53: 0.90697674 | AF53: 0.90697674 | AG53: 0.90697674 | AH53: 0.90697674 | AI53: 0.88372093 | AJ53: 0.86046512 | AK53: 0.81395349 | AL53: 0.81395349
A54: 2019Q4 | B54: 1 | C54: 1 | D54: 0.98076923 | E54: 0.98076923 | F54: 0.98076923 | G54: 0.98076923 | H54: 0.96153846 | I54: 0.96153846 | J54: 0.96153846 | K54: 0.94230769 | L54: 0.94230769 | M54: 0.94230769 | N54: 0.94230769 | O54: 0.92307692 | P54: 0.90384615 | Q54: 0.88461538 | R54: 0.88461538 | S54: 0.88461538 | T54: 0.88461538 | U54: 0.86538462 | V54: 0.86538462 | W54: 0.84615385 | X54: 0.84615385 | Y54: 0.80769231 | Z54: 0.80769231 | AA54: 0.80769231 | AB54: 0.78846154 | AC54: 0.78846154 | AD54: 0.78846154 | AE54: 0.78846154 | AF54: 0.78846154 | AG54: 0.78846154 | AH54: 0.78846154 | AI54: 0.78846154 | AJ54: 0.78846154 | AK54: 0.78846154 | AL54: 0.78846154
... A66: 2022Q4 | B66: 1 | C66: 1 | D66: 1 | E66: 1 | F66: 0.984375 | G66: 0.96875 | H66: 0.96875 | I66: 0.96875 | J66: 0.96875 | K66: 0.96875 | L66: 0.953125 | M66: 0.9375 | N66: 0.9375 | O66: 0.9375 | P66: 0.90625 | Q66: 0.890625 | R66: 0.875 | S66: 0.875 | T66: 0.875 | U66: 0.875 | V66: 0.875 | W66: 0.875 | X66: 0.859375 | Y66: 0.859375 | Z66: 0.84375 | AA66: 0.84375 | AB66: 0.84375 | AC66: 0.828125 | AD66: 0.8125 | AE66: 0.796875 | AF66: 0.765625 | AG66: 0.75 | AH66: 0.75 | AI66: 0.71875 | AJ66: 0.71875 | AK66: 0.71875 | AL66: 0.71875
A67: 2023Q1 | B67: 1 | C67: 0.98809524 | D67: 0.98809524 | E67: 0.98809524 | F67: 0.97619048 | G67: 0.95238095 | H67: 0.9047619 | I67: 0.9047619 | J67: 0.85714286 | K67: 0.85714286 | L67: 0.83333333 | M67: 0.80952381 | N67: 0.79761905 | O67: 0.77380952 | P67: 0.76190476 | Q67: 0.75 | R67: 0.73809524 | S67: 0.73809524 | T67: 0.70238095 | U67: 0.67857143 | V67: 0.6547619 | W67: 0.64285714 | X67: 0.63095238 | Y67: 0.5952381 | Z67: 0.5952381 | AA67: 0.55952381 | AB67: 0.54761905 | AC67: 0.54761905 | AD67: 0.54761905 | AE67: 0.51190476 | AF67: 0.5 | AG67: 0.47619048 | AH67: 0.47619048 | AI67: 0.46428571
A68: 2023Q2 | B68: 1 | C68: 1 | D68: 1 | E68: 1 | F68: 0.96428571 | G68: 0.96428571 | H68: 0.91666667 | I68: 0.88095238 | J68: 0.88095238 | K68: 0.88095238 | L68: 0.8452381 | M68: 0.82142857 | N68: 0.79761905 | O68: 0.78571429 | P68: 0.76190476 | Q68: 0.76190476 | R68: 0.72619048 | S68: 0.72619048 | T68: 0.71428571 | U68: 0.69047619 | V68: 0.67857143 | W68: 0.67857143 | X68: 0.67857143 | Y68: 0.67857143 | Z68: 0.6547619 | AA68: 0.64285714 | AB68: 0.64285714 | AC68: 0.63095238 | AD68: 0.60714286 | AE68: 0.5952381 | AF68: 0.5952381
A69: 2023Q3 | B69: 1 | C69: 1 | D69: 0.98333333 | E69: 0.98333333 | F69: 0.96666667 | G69: 0.96666667 | H69: 0.96666667 | I69: 0.96666667 | J69: 0.93333333 | K69: 0.91666667 | L69: 0.91666667 | M69: 0.9 | N69: 0.88333333 | O69: 0.88333333 | P69: 0.88333333 | Q69: 0.85 | R69: 0.85 | S69: 0.85 | T69: 0.85 | U69: 0.85 | V69: 0.83333333 | W69: 0.81666667 | X69: 0.8 | Y69: 0.76666667 | Z69: 0.75 | AA69: 0.75 | AB69: 0.73333333 | AC69: 0.73333333
A70: 2023Q4 | B70: 1 | C70: 1 | D70: 1 | E70: 1 | F70: 0.98780488 | G70: 0.98780488 | H70: 0.98780488 | I70: 0.96341463 | J70: 0.95121951 | K70: 0.90243902 | L70: 0.87804878 | M70: 0.85365854 | N70: 0.84146341 | O70: 0.84146341 | P70: 0.81707317 | Q70: 0.80487805 | R70: 0.7804878 | S70: 0.76829268 | T70: 0.76829268 | U70: 0.75609756 | V70: 0.75609756 | W70: 0.75609756 | X70: 0.74390244 | Y70: 0.7195122 | Z70: 0.69512195
A71: 2024Q1 | B71: 1 | C71: 1 | D71: 0.98666667 | E71: 0.98666667 | F71: 0.93333333 | G71: 0.93333333 | H71: 0.93333333 | I71: 0.89333333 | J71: 0.82666667 | K71: 0.8 | L71: 0.78666667 | M71: 0.78666667 | N71: 0.78666667 | O71: 0.77333333 | P71: 0.77333333 | Q71: 0.74666667 | R71: 0.73333333 | S71: 0.73333333 | T71: 0.72 | U71: 0.72 | V71: 0.68 | W71: 0.66666667
A72: 2024Q2 | B72: 1 | C72: 0.98876404 | D72: 0.97752809 | E72: 0.96629213 | F72: 0.93258427 | G72: 0.88764045 | H72: 0.87640449 | I72: 0.84269663 | J72: 0.80898876 | K72: 0.76404494 | L72: 0.75280899 | M72: 0.75280899 | N72: 0.73033708 | O72: 0.70786517 | P72: 0.6741573 | Q72: 0.6741573 | R72: 0.66292135 | S72: 0.65168539 | T72: 0.64044944
A73: 2024Q3 | B73: 1 | C73: 1 | D73: 0.98461538 | E73: 0.98461538 | F73: 0.98461538 | G73: 0.98461538 | H73: 0.95384615 | I73: 0.93846154 | J73: 0.86153846 | K73: 0.83076923 | L73: 0.8 | M73: 0.78461538 | N73: 0.76923077 | O73: 0.76923077 | P73: 0.72307692 | Q73: 0.70769231
A74: 2024Q4 | B74: 1 | C74: 0.97297297 | D74: 0.95945946 | E74: 0.93243243 | F74: 0.93243243 | G74: 0.86486486 | H74: 0.85135135 | I74: 0.81081081 | J74: 0.7972973 | K74: 0.77027027 | L74: 0.77027027 | M74: 0.72972973 | N74: 0.7027027
A75: 2025Q1 | B75: 1 | C75: 0.97826087 | D75: 0.95652174 | E75: 0.94565217 | F75: 0.90217391 | G75: 0.89130435 | H75: 0.86956522 | I75: 0.85869565 | J75: 0.84782609 | K75: 0.83695652
A76: 2025Q2 | B76: 1 | C76: 1 | D76: 0.98214286 | E76: 0.96428571 | F76: 0.92857143 | G76: 0.85714286 | H76: 0.83928571
A77: 2025Q3 | B77: 1 | C77: 0.98947368 | D77: 0.96842105 | E77: 0.96842105
A78: 2025Q4 | B78: 1

Sheet 4d NRR GRR
A1: 4d. Net and gross revenue retention (2023 to 2025 only: no December 2021 in the data)
A2: Units: £'000 for MRR; % for NRR and GRR
A3: Source: outputs/tables/4d_nrr_grr.csv, benchmarks.csv, 4d_benchmark_comparison.csv (notebooks/04d_nrr_grr.ipynb)
A5: NRR and GRR (December to December MRR)
A6: Basis | B6: Year | C6: Uplift factor k | D6: Opening MRR | E6: Closing MRR (same customers) | F6: Closing MRR capped at opening | G6: NRR | H6: GRR | I6: Customers at opening | J6: Customers retained
A7: reported | B7: 2023 | C7: 1 | D7: 2417140.3 | E7: 2314808.5 | F7: 2284726.4 | G7: =E7/D7 -> 0.95766411 | H7: =F7/D7 -> 0.94521877 | I7: 1010 | J7: 920
A8: excluding top 5 customers | B8: 2023 | C8: 1 | D8: 1711723.6 | E8: 1609391.8 | F8: 1579309.7 | G8: =E8/D8 -> 0.94021711 | H8: =F8/D8 -> 0.92264294 | I8: 1005 | J8: 915
A9: excluding price increase | B9: 2023 | C9: 1 | D9: 2417140.3 | E9: 2314808.5 | F9: 2284726.4 | G9: =E9/D9 -> 0.95766411 | H9: =F9/D9 -> 0.94521877 | I9: 1010 | J9: 920
A10: excluding top 5 and price increase | B10: 2023 | C10: 1 | D10: 1711723.6 | E10: 1609391.8 | F10: 1579309.7 | G10: =E10/D10 -> 0.94021711 | H10: =F10/D10 -> 0.92264294 | I10: 1005 | J10: 915
A11: reported | B11: 2024 | C11: 1.05 | D11: 2731778.5 | E11: 2697550.7 | F11: 2538154.4 | G11: =E11/D11 -> 0.98747049 | H11: =F11/D11 -> 0.92912156 | I11: 1205 | J11: 1073
A12: excluding top 5 customers | B12: 2024 | C12: 1.05 | D12: 2026361.9 | E12: 1975238.2 | F12: 1845279.4 | G12: =E12/D12 -> 0.97477071 | H12: =F12/D12 -> 0.91063663 | I12: 1200 | J12: 1068
A13: excluding price increase | B13: 2024 | C13: 1.05 | D13: 2731778.5 | E13: 2569095.9 | F13: 2531658.3 | G13: =E13/D13 -> 0.94044808 | H13: =F13/D13 -> 0.92674359 | I13: 1205 | J13: 1073
A14: excluding top 5 and price increase | B14: 2024 | C14: 1.05 | D14: 2026361.9 | E14: 1881179.2 | F14: 1843741.6 | G14: =E14/D14 -> 0.92835306 | H14: =F14/D14 -> 0.90987776 | I14: 1200 | J14: 1068
A15: reported | B15: 2025 | C15: 1.07 | D15: 3124736.3 | E15: 2982357 | F15: 2773798.8 | G15: =E15/D15 -> 0.95443477 | H15: =F15/D15 -> 0.88769051 | I15: 1343 | J15: 1172
A16: excluding top 5 customers | B16: 2025 | C16: 1.07 | D16: 2402423.9 | E16: 2337280.8 | F16: 2153773.8 | G16: =E16/D16 -> 0.97288444 | H16: =F16/D16 -> 0.89650034 | I16: 1338 | J16: 1167
A17: excluding price increase | B17: 2025 | C17: 1.07 | D17: 3124736.3 | E17: 2787249.5 | F17: 2755077.3 | G17: =E17/D17 -> 0.89199511 | H17: =F17/D17 -> 0.88169913 | I17: 1343 | J17: 1172
A18: excluding top 5 and price increase | B18: 2025 | C18: 1.07 | D18: 2402423.9 | E18: 2184374.5 | F18: 2152202.3 | G18: =E18/D18 -> 0.90923779 | H18: =F18/D18 -> 0.89584621 | I18: 1338 | J18: 1167
A20: Check: reported opening MRR × 12 equals prior-year ARR on the 4a tab | B20: =ABS(D7*12-SUMIFS('4a Revenue quality'!$B$15:$B$18,'4a Revenue quality'!$A$15:$A$18,B7-1))<0.01 -> TRUE | C20: =ABS(D11*12-SUMIFS('4a Revenue quality'!$B$15:$B$18,'4a Revenue quality'!$A$15:$A$18,B11-1))<0.01 -> TRUE | D20: =ABS(D15*12-SUMIFS('4a Revenue quality'!$B$15:$B$18,'4a Revenue quality'!$A$15:$A$18,B15-1))<0.01 -> TRUE
A22: For the chart
A23: Year | B23: NRR reported | C23: NRR excluding price increase | D23: GRR reported
A24: 2023 | B24: =SUMIFS($G$7:$G$18,$A$7:$A$18,"reported",$B$7:$B$18,2023) -> 0.95766411 | C24: =SUMIFS($G$7:$G$18,$A$7:$A$18,"excluding price increase",$B$7:$B$18,2023) -> 0.95766411 | D24: =SUMIFS($H$7:$H$18,$A$7:$A$18,"reported",$B$7:$B$18,2023) -> 0.94521877 | L24: DRAFT commentary for review (drafted from outputs/key_findings.md): F03 (High): Retention is weakening. NRR was 95.8%, 98.7% and 95.4% for 2023 to 2025; excluding the price increase it was 95.8%, 94.0% and 89.2%. GRR fell from 94.5% to 88.8%. Logo churn rose from 90 customers (8.9%) in 2023 to 171 (12.7%) in 2025. NRR and GRR are available for 2023 to 2025 only. Against sourced benchmarks, 2025 NRR and GRR are below the SaaS Capital medians for SMB software, whose definitions match ours (98% to 103% NRR, 90% to 91% GRR), and NRR before the price increase is below every SMB median in the three 2025 benchmark surveys (94% to 107%; GRR medians 83% to 92%); see docs/benchmarks.md.
A25: 2024 | B25: =SUMIFS($G$7:$G$18,$A$7:$A$18,"reported",$B$7:$B$18,2024) -> 0.98747049 | C25: =SUMIFS($G$7:$G$18,$A$7:$A$18,"excluding price increase",$B$7:$B$18,2024) -> 0.94044808 | D25: =SUMIFS($H$7:$H$18,$A$7:$A$18,"reported",$B$7:$B$18,2024) -> 0.92912156
A26: 2025 | B26: =SUMIFS($G$7:$G$18,$A$7:$A$18,"reported",$B$7:$B$18,2025) -> 0.95443477 | C26: =SUMIFS($G$7:$G$18,$A$7:$A$18,"excluding price increase",$B$7:$B$18,2025) -> 0.89199511 | D26: =SUMIFS($H$7:$H$18,$A$7:$A$18,"reported",$B$7:$B$18,2025) -> 0.88769051
A28: What good looks like: sourced SMB benchmarks (medians for ACV bands under US$50k; see docs/benchmarks.md)
A29: Source | B29: Publisher | C29: Edition | D29: Segment | E29: Metric | F29: Median
A30: SC25 | B30: SaaS Capital | C30: 2025 | D30: SMB: ACV under $12k | E30: NRR | F30: 0.98
A31: SC25 | B31: SaaS Capital | C31: 2025 | D31: SMB: ACV $12k to $25k | E31: NRR | F31: 1.03
A32: SC25 | B32: SaaS Capital | C32: 2025 | D32: SMB: ACV $25k to $50k | E32: NRR | F32: 1.02
A33: HA25 | B33: High Alpha | C33: 2025 | D33: SMB: ACV under $1k | E33: NRR | F33: 0.98
A34: HA25 | B34: High Alpha | C34: 2025 | D34: SMB: ACV $1k to $5k | E34: NRR | F34: 0.97
A35: HA25 | B35: High Alpha | C35: 2025 | D35: SMB: ACV $5k to $10k | E35: NRR | F35: 0.94
A36: HA25 | B36: High Alpha | C36: 2025 | D36: SMB: ACV $10k to $15k | E36: NRR | F36: 1.07
A37: HA25 | B37: High Alpha | C37: 2025 | D37: SMB: ACV $15k to $25k | E37: NRR | F37: 1.04
A38: HA25 | B38: High Alpha | C38: 2025 | D38: SMB: ACV $25k to $50k | E38: NRR | F38: 1.05
A39: BM25 | B39: Benchmarkit | C39: 2025 | D39: SMB: ACV under $1k | E39: NRR | F39: 1
A40: BM25 | B40: Benchmarkit | C40: 2025 | D40: SMB: ACV $1k to $5k | E40: NRR | F40: 0.99
A41: BM25 | B41: Benchmarkit | C41: 2025 | D41: SMB: ACV $5k to $10k | E41: NRR | F41: 1
... A57: BM25 | B57: Benchmarkit | C57: 2025 | D57: SMB: ACV $25k to $50k | E57: GRR | F57: 0.88
A59: Measure | B59: SMB median, low | C59: SMB median, high | D59: SaaS Capital SMB median, low | E59: SaaS Capital SMB median, high | F59: Northbridge 2025 | G59: Per 4d notebook: low | H59: Per 4d notebook: high | I59: Check
A60: NRR | B60: =MIN(F30:F43) -> 0.94 | C60: =MAX(F30:F43) -> 1.07 | D60: =MIN(F30:F32) -> 0.98 | E60: =MAX(F30:F32) -> 1.03 | F60: =G15 -> 0.95443477 | G60: 0.94 | H60: 1.07 | I60: =AND(ABS(B60-G60)<0.000001,ABS(C60-H60)<0.000001) -> TRUE
A61: NRR before price increase | B61: =MIN(F30:F43) -> 0.94 | C61: =MAX(F30:F43) -> 1.07 | D61: =MIN(F30:F32) -> 0.98 | E61: =MAX(F30:F32) -> 1.03 | F61: =G17 -> 0.89199511 | G61: 0.94 | H61: 1.07 | I61: =AND(ABS(B61-G61)<0.000001,ABS(C61-H61)<0.000001) -> TRUE
A62: GRR | B62: =MIN(F44:F57) -> 0.83 | C62: =MAX(F44:F57) -> 0.92 | D62: =MIN(F44:F46) -> 0.9 | E62: =MAX(F44:F46) -> 0.91 | F62: =H15 -> 0.88769051 | G62: 0.83 | H62: 0.92 | I62: =AND(ABS(B62-G62)<0.000001,ABS(C62-H62)<0.000001) -> TRUE
A64: Sources: SaaS Capital, 2025 B2B SaaS Retention Benchmarks (Research Brief 32) (2025), https://www.saas-capital.com/wp-content/uploads/2025/09/RB32WS1-2025-B2B-SaaS-Retention-Benchmarks.pdf, accessed 2026-09-26; High Alpha, 2025 SaaS Benchmarks Report (2025), https://2994607.fs1.hubspotusercontent-na1.net/hubfs/2994607/2025%20SaaS%20Benchmarks%20Report.pdf, accessed 2026-09-26; Benchmarkit, 2025 B2B SaaS Performance Metrics Benchmarks (2025), https://www.benchmarkit.ai/_files/ugd/2a084b_1b2e8054260b44cba36242807d1c3eea.pdf, accessed 2026-09-26. Only SaaS Capital uses our definitions (December-to-December MRR, price increases in NRR, GRR capped at opening MRR); the others do not state how price increases are treated. Bands are in US dollars; Northbridge's average ACV is in pounds. Medians place Northbridge in a distribution of private SaaS companies, largely US-based where stated; they are not a pass mark.

Sheet 4e ARR bridge
A1: 4e. ARR bridge and revenue bridge
A2: Units: £'000
A3: Source: outputs/tables/4e_arr_bridge.csv, 4e_revenue_bridge.csv (notebooks/04e_arr_bridge.ipynb)
A5: ARR bridge (December MRR × 12, customer × product line)
A6: £'000 | B6: 2023 | C6: 2024 | D6: 2025
A7: Opening ARR | B7: 29005684 | C7: =B15 -> 32781343 | D7: =C15 -> 37496836
A8: New customers | B8: 5003640.5 | C8: 5126227.7 | D8: 5571543.6
A9: Cross-sell | B9: 360985.44 | C9: 471697.92 | D9: 413062.32
A10: Upsell | B10: 0 | C10: 0 | D10: 0
A11: Price increase | B11: 0 | C11: 1518997.1 | D11: 2314269.2
A12: Downgrade | B12: -79064.4 | C12: -314614.2 | D12: -1529874.1
A13: Contraction | B13: 0 | C13: 0 | D13: 0
A14: Churn | B14: -1509902.5 | C14: -2086815 | D14: -2906009.3
A15: Closing ARR | B15: =SUM(B7:B14) -> 32781343 | C15: =SUM(C7:C14) -> 37496836 | D15: =SUM(D7:D14) -> 41359828
A16: Closing ARR per cube | B16: =SUMIFS('4a Revenue quality'!$B$15:$B$18,'4a Revenue quality'!$A$15:$A$18,2023) -> 32781343 | C16: =SUMIFS('4a Revenue quality'!$B$15:$B$18,'4a Revenue quality'!$A$15:$A$18,2024) -> 37496836 | D16: =SUMIFS('4a Revenue quality'!$B$15:$B$18,'4a Revenue quality'!$A$15:$A$18,2025) -> 41359828
A17: Check | B17: =AND(ABS(B15-B16)<0.01,ABS(B7-SUMIFS('4a Revenue quality'!$B$15:$B$18,'4a Revenue quality'!$A$15:$A$18,2022))<0.01) -> TRUE | C17: =AND(ABS(C15-C16)<0.01,ABS(C7-SUMIFS('4a Revenue quality'!$B$15:$B$18,'4a Revenue quality'!$A$15:$A$18,2023))<0.01) -> TRUE | D17: =AND(ABS(D15-D16)<0.01,ABS(D7-SUMIFS('4a Revenue quality'!$B$15:$B$18,'4a Revenue quality'!$A$15:$A$18,2024))<0.01) -> TRUE
A19: Waterfall helper, 2025 (formulas)
A20: Component | B20: Base | C20: Increase | D20: Decrease | E20: Total
A21: Opening ARR | B21: =0 -> 0 | C21: =0 -> 0 | D21: =0 -> 0 | E21: =D7 -> 37496836
A22: New customers | B22: =MIN(SUM($D$7:D7),SUM($D$7:D7)+D8) -> 37496836 | C22: =MAX(D8,0) -> 5571543.6 | D22: =MAX(-D8,0) -> 0 | E22: =0 -> 0
A23: Cross-sell | B23: =MIN(SUM($D$7:D8),SUM($D$7:D8)+D9) -> 43068380 | C23: =MAX(D9,0) -> 413062.32 | D23: =MAX(-D9,0) -> 0 | E23: =0 -> 0
A24: Upsell | B24: =MIN(SUM($D$7:D9),SUM($D$7:D9)+D10) -> 43481442 | C24: =MAX(D10,0) -> 0 | D24: =MAX(-D10,0) -> 0 | E24: =0 -> 0
A25: Price increase | B25: =MIN(SUM($D$7:D10),SUM($D$7:D10)+D11) -> 43481442 | C25: =MAX(D11,0) -> 2314269.2 | D25: =MAX(-D11,0) -> 0 | E25: =0 -> 0
A26: Downgrade | B26: =MIN(SUM($D$7:D11),SUM($D$7:D11)+D12) -> 44265837 | C26: =MAX(D12,0) -> 0 | D26: =MAX(-D12,0) -> 1529874.1 | E26: =0 -> 0 | J26: DRAFT commentary for review (drafted from outputs/key_findings.md): F02 (High): Price increases carry a large part of recurring growth. Every recurring line was billed 5% more from January 2024 and a further 7% from January 2025. ARR grew 10.3% in 2025, 3.1% before the price increase (14.4% and 8.9% in 2024). The price increase added £2.31m of ARR in 2025; upsell was £0. F10 (Medium): 2025 revenue rose £8.50m: other implementation £4.08m, new customers £3.07m, full-year effect of 2024 additions £2.18m, price £2.46m and cross-sell £0.28m, less churn £2.64m and downgrades £0.90m.
A27: Contraction | B27: =MIN(SUM($D$7:D12),SUM($D$7:D12)+D13) -> 44265837 | C27: =MAX(D13,0) -> 0 | D27: =MAX(-D13,0) -> 0 | E27: =0 -> 0
A28: Churn | B28: =MIN(SUM($D$7:D13),SUM($D$7:D13)+D14) -> 41359828 | C28: =MAX(D14,0) -> 0 | D28: =MAX(-D14,0) -> 2906009.3 | E28: =0 -> 0
A29: Closing ARR | B29: =0 -> 0 | C29: =0 -> 0 | D29: =0 -> 0 | E29: =D15 -> 41359828
A32: Revenue bridge: year-on-year change in net revenue
A33: £'000 | B33: 2023 | C33: 2024 | D33: 2025
A34: Prior-year net revenue | B34: 28232152 | C34: 32192870 | D34: 37258899
A35: New customers | B35: 2884583.6 | C35: 2982907.4 | D35: 3068356
A36: Full-year effect of prior-year additions | B36: 2039767.8 | C36: 2273217.2 | D36: 2183163.6
A37: Cross-sell | B37: 196902.61 | C37: 278899.86 | D37: 278670.58
A38: Upsell | B38: 0 | C38: 403.98 | D38: 0
A39: Price increase | B39: 0 | C39: 1579728.1 | D39: 2455688.2
A40: Billing gaps | B40: -3911.95 | C40: -1752.89 | D40: -1740.79
A41: Downgrade | B41: -76395.5 | C41: -196870.77 | D41: -896690.15
A42: Contraction | B42: 0 | C42: 0 | D42: 0
A43: Churn | B43: -1326723.4 | C43: -1772194.7 | D43: -2639571.8
A44: Change in credit notes | B44: 52150.89 | C44: -44320.63 | D44: -87462.16
A45: Change in signup implementation | B45: 194344.21 | C45: -33988.98 | D45: 60533.07
A46: Change in other implementation | B46: 0 | C46: 0 | D46: 4076574.3
A47: Net revenue | B47: =SUM(B34:B46) -> 32192870 | C47: =SUM(C34:C46) -> 37258899 | D47: =SUM(D34:D46) -> 45756419
A48: Net revenue per 4a | B48: =SUMIFS('4a Revenue quality'!$F$7:$F$10,'4a Revenue quality'!$A$7:$A$10,2023) -> 32192870 | C48: =SUMIFS('4a Revenue quality'!$F$7:$F$10,'4a Revenue quality'!$A$7:$A$10,2024) -> 37258899 | D48: =SUMIFS('4a Revenue quality'!$F$7:$F$10,'4a Revenue quality'!$A$7:$A$10,2025) -> 45756419
A49: Check | B49: =ABS(B47-B48)<0.01 -> TRUE | C49: =ABS(C47-C48)<0.01 -> TRUE | D49: =ABS(D47-D48)<0.01 -> TRUE
A50: Of which recurring change | B50: =SUM(B35:B44) -> 3766374.1 | C50: =SUM(C35:C44) -> 5100017.5 | D50: =SUM(D35:D44) -> 4360413.5
A51: Of which one-off change | B51: =SUM(B45:B46) -> 194344.21 | C51: =SUM(C45:C46) -> -33988.98 | D51: =SUM(D45:D46) -> 4137107.4

Sheet 4f Margin
A1: 4f. Gross margin: by product line, mix and rate, size band and discounting
A2: Units: £'000 unless stated
A3: Source: outputs/tables/4f_*.csv (notebooks/04f_margins.ipynb); costs from costs.csv
A5: Revenue
A6: Product line | B6: 2022 | C6: 2023 | D6: 2024 | E6: 2025
A7: Core Platform | B7: 20979314 | C7: 23830469 | D7: 27735969 | E7: 31584836
A8: Analytics Add-on | B8: 3078864.2 | C8: 3594489.9 | D8: 4168383.6 | E8: 4574888.4
A9: Payments Module | B9: 3190113.9 | C9: 3589707 | D9: 4210331.4 | E9: 4315372.4
A10: Implementation Services | B10: 983859.59 | C10: 1178203.8 | D10: 1144214.8 | E10: 5281322.2
A11: Total | B11: =SUM(B7:B10) -> 28232152 | C11: =SUM(C7:C10) -> 32192870 | D11: =SUM(D7:D10) -> 37258899 | E11: =SUM(E7:E10) -> 45756419
A13: Cost of delivery
A14: Product line | B14: 2022 | C14: 2023 | D14: 2024 | E14: 2025
A15: Core Platform | B15: 3863844.9 | C15: 4363175.6 | D15: 5040485 | E15: 5662706.5
A16: Analytics Add-on | B16: 681022.94 | C16: 800746.9 | D16: 937570.01 | E16: 1018543.2
A17: Payments Module | B17: 1101125.7 | C17: 1272684.8 | D17: 1494750.8 | E17: 1475499.7
A18: Implementation Services | B18: 721078.85 | C18: 840341.31 | D18: 803287.42 | E18: 3851384.2
A19: Total | B19: =SUM(B15:B18) -> 6367072.3 | C19: =SUM(C15:C18) -> 7276948.6 | D19: =SUM(D15:D18) -> 8276093.2 | E19: =SUM(E15:E18) -> 12008134
A21: Gross profit
A22: Product line | B22: 2022 | C22: 2023 | D22: 2024 | E22: 2025
A23: Core Platform | B23: =B7-B15 -> 17115469 | C23: =C7-C15 -> 19467294 | D23: =D7-D15 -> 22695484 | E23: =E7-E15 -> 25922130
A24: Analytics Add-on | B24: =B8-B16 -> 2397841.3 | C24: =C8-C16 -> 2793743 | D24: =D8-D16 -> 3230813.6 | E24: =E8-E16 -> 3556345.1 | K24: DRAFT commentary for review (drafted from outputs/key_findings.md): F06 (Medium): Gross margin fell from 77.8% to 73.8% in 2025, entirely through mix: the mix effect was -4.03 points and the rate effect +0.00. Implementation Services earns 27.1%, and its cost of delivery rose from £0.80m to £3.85m, so the 2025 implementation revenue came with its delivery cost. F07 (Medium): Discounts gave up £5.35m of list-price revenue in 2025 (11.6% of list). Large customers average 22.2% off list and account for 74.7% of the revenue given up.
A25: Payments Module | B25: =B9-B17 -> 2088988.2 | C25: =C9-C17 -> 2317022.3 | D25: =D9-D17 -> 2715580.6 | E25: =E9-E17 -> 2839872.7
A26: Implementation Services | B26: =B10-B18 -> 262780.74 | C26: =C10-C18 -> 337862.49 | D26: =D10-D18 -> 340927.4 | E26: =E10-E18 -> 1429938
A28: Gross margin
A29: Product line | B29: 2022 | C29: 2023 | D29: 2024 | E29: 2025
A30: Core Platform | B30: =B23/B7 -> 0.81582597 | C30: =C23/C7 -> 0.81690769 | D30: =D23/D7 -> 0.81826901 | E30: =E23/E7 -> 0.82071439
A31: Analytics Add-on | B31: =B24/B8 -> 0.77880709 | C31: =C24/C8 -> 0.77722934 | D31: =D24/D8 -> 0.77507588 | E31: =E24/E8 -> 0.77736216
A32: Payments Module | B32: =B25/B9 -> 0.65483187 | C32: =C25/C9 -> 0.64546277 | D32: =D25/D9 -> 0.64498026 | E32: =E25/E9 -> 0.65808287
A33: Implementation Services | B33: =B26/B10 -> 0.26709171 | C33: =C26/C10 -> 0.28676065 | D33: =D26/D10 -> 0.29795751 | E33: =E26/E10 -> 0.27075378
A35: Revenue share
A36: Product line | B36: 2022 | C36: 2023 | D36: 2024 | E36: 2025
A37: Core Platform | B37: =B7/B$11 -> 0.74310007 | C37: =C7/C$11 -> 0.74024059 | D37: =D7/D$11 -> 0.74441193 | E37: =E7/E$11 -> 0.69028208
A38: Analytics Add-on | B38: =B8/B$11 -> 0.10905525 | C38: =C8/C$11 -> 0.11165484 | D38: =D8/D$11 -> 0.11187619 | E38: =E8/E$11 -> 0.099983531
A39: Payments Module | B39: =B9/B$11 -> 0.11299578 | C39: =C9/C$11 -> 0.11150628 | D39: =D9/D$11 -> 0.11300204 | E39: =E9/E$11 -> 0.094311847
A40: Implementation Services | B40: =B10/B$11 -> 0.034848906 | C40: =C10/C$11 -> 0.036598284 | D40: =D10/D$11 -> 0.03070984 | E40: =E10/E$11 -> 0.11542254
A41: Blended margin and its movement
A42: Blended gross profit | B42: =B11-B19 -> 21865079 | C42: =C11-C19 -> 24915921 | D42: =D11-D19 -> 28982805 | E42: =E11-E19 -> 33748286
A43: Blended gross margin | B43: =B42/B11 -> 0.77447442 | C43: =C42/C11 -> 0.77395776 | D43: =D42/D11 -> 0.77787607 | E43: =E42/E11 -> 0.73756396
A44: Change in blended margin (pts) | C44: =(C43-B43)*100 -> -0.051666637 | D44: =(D43-C43)*100 -> 0.39183095 | E44: =(E43-D43)*100 -> -4.031211
A45: Mix effect (pts) | C45: =SUMPRODUCT(C37:C40-B37:B40,B30:B33)*100 -> -0.08163772 | D45: =SUMPRODUCT(D37:D40-C37:C40,C30:C33)*100 -> 0.2856518 | E45: =SUMPRODUCT(E37:E40-D37:D40,D30:D33)*100 -> -4.0324512
A46: Rate effect (pts) | C46: =SUMPRODUCT(C37:C40,C30:C33-B30:B33)*100 -> 0.029971083 | D46: =SUMPRODUCT(D37:D40,D30:D33-C30:C33)*100 -> 0.10617915 | E46: =SUMPRODUCT(E37:E40,E30:E33-D30:D33)*100 -> 0.001240234
A47: Check: mix + rate = change | C47: =ABS(C45+C46-C44)<0.000001 -> TRUE | D47: =ABS(D45+D46-D44)<0.000001 -> TRUE | E47: =ABS(E45+E46-E44)<0.000001 -> TRUE
A49: Reconciliation to management gross profit
A50: Mgmt total revenue | B50: 28232152 | C50: 32174370 | D50: 37261399 | E50: 45771419
A51: Mgmt cost of sales | B51: 6367072.3 | C51: 7276948.6 | D51: 8276093.2 | E51: 12008134
A52: Mgmt gross profit | B52: =B50-B51 -> 21865079 | C52: =C50-C51 -> 24897421 | D52: =D50-D51 -> 28985305 | E52: =E50-E51 -> 33763286
A53: Invoice-based gross profit | B53: =B42 -> 21865079 | C53: =C42 -> 24915921 | D53: =D42 -> 28982805 | E53: =E42 -> 33748286
A54: Difference | B54: =B52-B53 -> 0 | C54: =C52-C53 -> -18500 | D54: =D52-D53 -> 2500 | E54: =E52-E53 -> 15000
A55: Unexplained adjustments to reported revenue (Reconciliation tab) | B55: =-SUMIFS(Reconciliation!$D$59:$D$62,Reconciliation!$A$59:$A$62,2022) -> 0 | C55: =-SUMIFS(Reconciliation!$D$59:$D$62,Reconciliation!$A$59:$A$62,2023) -> -18500 | D55: =-SUMIFS(Reconciliation!$D$59:$D$62,Reconciliation!$A$59:$A$62,2024) -> 2500 | E55: =-SUMIFS(Reconciliation!$D$59:$D$62,Reconciliation!$A$59:$A$62,2025) -> 15000
A56: Check | B56: =AND(ABS(B54-B55)<0.01,ABS(B51-B19)<0.01) -> TRUE | C56: =AND(ABS(C54-C55)<0.01,ABS(C51-C19)<0.01) -> TRUE | D56: =AND(ABS(D54-D55)<0.01,ABS(D51-D19)<0.01) -> TRUE | E56: =AND(ABS(E54-E55)<0.01,ABS(E51-E19)<0.01) -> TRUE
A59: Discounting: recurring billings against list-equivalent
A60: Year | B60: Recurring billings | C60: List-equivalent | D60: Revenue given up | E60: Discount % of list | F60: Gross margin actual | G60: Gross margin at list
A61: 2022 | B61: 27577497 | C61: 31930682 | D61: =C61-B61 -> 4353185.3 | E61: =D61/C61 -> 0.13633236 | F61: =B43 -> 0.77447442 | G61: =(B11+D61-B19)/(B11+D61) -> 0.80460315
A62: 2023 | B62: 31291720 | C62: 35911719 | D62: =C62-B62 -> 4619999.1 | E62: =D62/C62 -> 0.12864879 | F62: =C43 -> 0.77395776 | G62: =(C11+D62-C19)/(C11+D62) -> 0.80232596
A63: 2024 | B63: 36436058 | C63: 41527749 | D63: =C63-B63 -> 5091690.9 | E63: =D63/C63 -> 0.12260936 | F63: =D43 -> 0.77787607 | G63: =(D11+D63-D19)/(D11+D63) -> 0.80458139
A64: 2025 | B64: 40883934 | C64: 46238839 | D64: =C64-B64 -> 5354905.7 | E64: =D64/C64 -> 0.11580969 | F64: =E43 -> 0.73756396 | G64: =(E11+D64-E19)/(E11+D64) -> 0.76505924
A66: Discount by size band, 2025
A67: Size band | B67: Recurring billings | C67: List-equivalent | D67: Revenue given up | E67: Discount % of list | F67: Share of revenue given up
A68: Micro (1-9) | B68: 4740760.6 | C68: 4782416.5 | D68: =C68-B68 -> 41655.91 | E68: =D68/C68 -> 0.0087102221 | F68: =D68/SUM($D$68:$D$71) -> 0.0077790184
A69: Small (10-49) | B69: 10781514 | C69: 11123179 | D69: =C69-B69 -> 341664.49 | E69: =D69/C69 -> 0.030716444 | F69: =D69/SUM($D$68:$D$71) -> 0.063804016
A70: Medium (50-249) | B70: 11356310 | C70: 12329577 | D70: =C70-B70 -> 973267.29 | E70: =D70/C70 -> 0.078937603 | F70: =D70/SUM($D$68:$D$71) -> 0.18175246
A71: Large (250+) | B71: 14005349 | C71: 18003667 | D71: =C71-B71 -> 3998318 | E71: =D71/C71 -> 0.22208354 | F71: =D71/SUM($D$68:$D$71) -> 0.7466645
A72: Total | B72: =SUM(B68:B71) -> 40883934 | C72: =SUM(C68:C71) -> 46238839 | D72: =SUM(D68:D71) -> 5354905.7 | E72: =ABS(D72-D64)<0.01 -> TRUE
A74: Margin by size band, 2025 (basis A: cost pro rata to revenue; basis B: cost per active customer line)
A75: Size band | B75: Net revenue | C75: Cost basis A | D75: Cost basis B | E75: Margin basis A | F75: Margin basis B | G75: Customers
A76: Micro (1-9) | B76: 5678883.8 | C76: 1674557 | D76: 2808105 | E76: =(B76-C76)/B76 -> 0.70512568 | F76: =(B76-D76)/B76 -> 0.50551814 | G76: 443
A77: Small (10-49) | B77: 12761233 | C77: 3674483.9 | D77: 4691364.4 | E77: =(B77-C77)/B77 -> 0.71205887 | F77: =(B77-D77)/B77 -> 0.63237374 | G77: 682
A78: Medium (50-249) | B78: 12785193 | C78: 3350023 | D78: 3258431.4 | E78: =(B78-C78)/B78 -> 0.73797636 | F78: =(B78-D78)/B78 -> 0.74514024 | G78: 415
A79: Large (250+) | B79: 14531109 | C79: 3309069.9 | D79: 1250232.9 | E79: =(B79-C79)/B79 -> 0.77227685 | F79: =(B79-D79)/B79 -> 0.91396163 | G79: 132
A80: Total | B80: =SUM(B76:B79) -> 45756419 | C80: =SUM(C76:C79) -> 12008134 | D80: =AND(ABS(B80-E11)<0.05,ABS(C80-E19)<0.05) -> TRUE

Sheet 4g Segments
A1: 4g. Segment cuts: revenue, growth, logo churn and NRR (2025)
A2: Units: £'000 unless stated
A3: Source: outputs/tables/4g_segments.csv (notebooks/04g_segments.ipynb). Logo churn and NRR are annual (December 2024 to December 2025), not tenure-matched
A5: Segments (flag: risk if logo churn is 5 points above the company rate or NRR 5 points below; small if fewer than 30 customers)
A6: Segment | B6: Dimension | C6: Customers Dec 2024 | D6: Churned in 2025 | E6: Opening MRR | F6: Closing MRR | G6: Closing MRR capped | H6: Net revenue 2024 | I6: Net revenue 2025 | J6: Growth | K6: Logo churn | L6: NRR | M6: GRR | N6: Flag
A7: Construction | B7: industry | C7: 146 | D7: 22 | E7: 327367.38 | F7: 318244.77 | G7: 294969.42 | H7: 3909763.9 | I7: 4758042.6 | J7: =I7/H7-1 -> 0.21696416 | K7: =D7/C7 -> 0.15068493 | L7: =F7/E7 -> 0.97213342 | M7: =G7/E7 -> 0.90103486 | N7: =IF(C7<30,"too small to conclude",IF(OR(K7>$K$30+0.05,L7<$L$30-0.05),"risk",IF(OR(K7<$K$30-0.05,L7>$L$30+0.05),"strength","none"))) -> none
A8: Education | B8: industry | C8: 116 | D8: 16 | E8: 268025.37 | F8: 264773.25 | G8: 244667.29 | H8: 3195148.6 | I8: 3860238.3 | J8: =I8/H8-1 -> 0.20815612 | K8: =D8/C8 -> 0.13793103 | L8: =F8/E8 -> 0.98786637 | M8: =G8/E8 -> 0.91285123 | N8: =IF(C8<30,"too small to conclude",IF(OR(K8>$K$30+0.05,L8<$L$30-0.05),"risk",IF(OR(K8<$K$30-0.05,L8>$L$30+0.05),"strength","none"))) -> none
A9: Financial Services | B9: industry | C9: 109 | D9: 16 | E9: 357940.44 | F9: 329751.24 | G9: 317695.18 | H9: 4238079.9 | I9: 4686039.8 | J9: =I9/H9-1 -> 0.10569878 | K9: =D9/C9 -> 0.14678899 | L9: =F9/E9 -> 0.92124612 | M9: =G9/E9 -> 0.88756437 | N9: =IF(C9<30,"too small to conclude",IF(OR(K9>$K$30+0.05,L9<$L$30-0.05),"risk",IF(OR(K9<$K$30-0.05,L9>$L$30+0.05),"strength","none"))) -> none
A10: Healthcare | B10: industry | C10: 123 | D10: 13 | E10: 425751.53 | F10: 337995.38 | G10: 319961.79 | H10: 5078933.6 | I10: 5434927.8 | J10: =I10/H10-1 -> 0.070092315 | K10: =D10/C10 -> 0.10569106 | L10: =F10/E10 -> 0.79387943 | M10: =G10/E10 -> 0.75152235 | N10: =IF(C10<30,"too small to conclude",IF(OR(K10>$K$30+0.05,L10<$L$30-0.05),"risk",IF(OR(K10<$K$30-0.05,L10>$L$30+0.05),"strength","none"))) -> risk
A11: Hospitality | B11: industry | C11: 122 | D11: 11 | E11: 219929.67 | F11: 219323.31 | G11: 202355.02 | H11: 2548317.7 | I11: 3876245.8 | J11: =I11/H11-1 -> 0.52109992 | K11: =D11/C11 -> 0.090163934 | L11: =F11/E11 -> 0.99724294 | M11: =G11/E11 -> 0.92008968 | N11: =IF(C11<30,"too small to conclude",IF(OR(K11>$K$30+0.05,L11<$L$30-0.05),"risk",IF(OR(K11<$K$30-0.05,L11>$L$30+0.05),"strength","none"))) -> none
A12: Logistics | B12: industry | C12: 122 | D12: 12 | E12: 204702.24 | F12: 199780.25 | G12: 184551.28 | H12: 2484343.5 | I12: 3286180.3 | J12: =I12/H12-1 -> 0.32275605 | K12: =D12/C12 -> 0.098360656 | L12: =F12/E12 -> 0.97595537 | M12: =G12/E12 -> 0.90155965 | N12: =IF(C12<30,"too small to conclude",IF(OR(K12>$K$30+0.05,L12<$L$30-0.05),"risk",IF(OR(K12<$K$30-0.05,L12>$L$30+0.05),"strength","none"))) -> none
A13: Manufacturing | B13: industry | C13: 132 | D13: 20 | E13: 224792.53 | F13: 224252.01 | G13: 204790.38 | H13: 2669583.5 | I13: 3744853.4 | J13: =I13/H13-1 -> 0.40278566 | K13: =D13/C13 -> 0.15151515 | L13: =F13/E13 -> 0.99759547 | M13: =G13/E13 -> 0.91101951 | N13: =IF(C13<30,"too small to conclude",IF(OR(K13>$K$30+0.05,L13<$L$30-0.05),"risk",IF(OR(K13<$K$30-0.05,L13>$L$30+0.05),"strength","none"))) -> none
A14: Professional Services | B14: industry | C14: 125 | D14: 15 | E14: 209867.94 | F14: 199196.26 | G14: 184441.36 | H14: 2519301.2 | I14: 3160364.2 | J14: =I14/H14-1 -> 0.25446066 | K14: =D14/C14 -> 0.12 | L14: =F14/E14 -> 0.9491505 | M14: =G14/E14 -> 0.87884486 | N14: =IF(C14<30,"too small to conclude",IF(OR(K14>$K$30+0.05,L14<$L$30-0.05),"risk",IF(OR(K14<$K$30-0.05,L14>$L$30+0.05),"strength","none"))) -> none
A15: Retail | B15: industry | C15: 135 | D15: 16 | E15: 405055.35 | F15: 410926.89 | G15: 380675.12 | H15: 4788080.7 | I15: 5833271 | J15: =I15/H15-1 -> 0.21829003 | K15: =D15/C15 -> 0.11851852 | L15: =F15/E15 -> 1.0144956 | M15: =G15/E15 -> 0.93981013 | N15: =IF(C15<30,"too small to conclude",IF(OR(K15>$K$30+0.05,L15<$L$30-0.05),"risk",IF(OR(K15<$K$30-0.05,L15>$L$30+0.05),"strength","none"))) -> strength
A16: Technology | B16: industry | C16: 132 | D16: 22 | E16: 331559.06 | F16: 333514.53 | G16: 307345.03 | H16: 3998957.5 | I16: 5010330.6 | J16: =I16/H16-1 -> 0.25290917 | K16: =D16/C16 -> 0.16666667 | L16: =F16/E16 -> 1.0058978 | M16: =G16/E16 -> 0.92696918 | N16: =IF(C16<30,"too small to conclude",IF(OR(K16>$K$30+0.05,L16<$L$30-0.05),"risk",IF(OR(K16<$K$30-0.05,L16>$L$30+0.05),"strength","none"))) -> strength
A17: Unknown | B17: industry | C17: 81 | D17: 8 | E17: 149744.83 | F17: 144599.13 | G17: 132346.91 | H17: 1828388.5 | I17: 2105925.6 | J17: =I17/H17-1 -> 0.15179326 | K17: =D17/C17 -> 0.098765432 | L17: =F17/E17 -> 0.96563688 | M17: =G17/E17 -> 0.88381622 | N17: =IF(C17<30,"too small to conclude",IF(OR(K17>$K$30+0.05,L17<$L$30-0.05),"risk",IF(OR(K17<$K$30-0.05,L17>$L$30+0.05),"strength","none"))) -> none
A18: EU | B18: region_group | C18: 95 | D18: 11 | E18: 233192.44 | F18: 237807.55 | G18: 219131.2 | H18: 2791258.4 | I18: 3389710.6 | J18: =I18/H18-1 -> 0.2144023 | K18: =D18/C18 -> 0.11578947 | L18: =F18/E18 -> 1.019791 | M18: =G18/E18 -> 0.93970113 | N18: =IF(C18<30,"too small to conclude",IF(OR(K18>$K$30+0.05,L18<$L$30-0.05),"risk",IF(OR(K18<$K$30-0.05,L18>$L$30+0.05),"strength","none"))) -> strength
... A23: Partner/Reseller | B23: acquisition_channel | C23: 223 | D23: 44 | E23: 356936.05 | F23: 309699.27 | G23: 287627.72 | H23: 4361213.2 | I23: 5149402.2 | J23: =I23/H23-1 -> 0.18072701 | K23: =D23/C23 -> 0.19730942 | L23: =F23/E23 -> 0.86766038 | M23: =G23/E23 -> 0.80582424 | N23: =IF(C23<30,"too small to conclude",IF(OR(K23>$K$30+0.05,L23<$L$30-0.05),"risk",IF(OR(K23<$K$30-0.05,L23>$L$30+0.05),"strength","none"))) -> risk
A24: Referral | B24: acquisition_channel | C24: 164 | D24: 18 | E24: 287977.23 | F24: 282035.21 | G24: 261055.76 | H24: 3433981.4 | I24: 4233275.2 | J24: =I24/H24-1 -> 0.23276009 | K24: =D24/C24 -> 0.1097561 | L24: =F24/E24 -> 0.97936635 | M24: =G24/E24 -> 0.90651528 | N24: =IF(C24<30,"too small to conclude",IF(OR(K24>$K$30+0.05,L24<$L$30-0.05),"risk",IF(OR(K24<$K$30-0.05,L24>$L$30+0.05),"strength","none"))) -> none | P24: DRAFT commentary for review (drafted from outputs/key_findings.md): F09 (Medium): Paid Search and Partner/Reseller customers churn fastest (19.5% and 19.7% in 2025, against 8.6% for Direct Sales). Healthcare NRR was 79.4% in 2025, driven by one large customer.
A25: Large (250+) | B25: company_size | C25: 117 | D25: 5 | E25: 1135206.8 | F25: 1075853 | G25: 1020918.8 | H25: 13628047 | I25: 14531109 | J25: =I25/H25-1 -> 0.06626498 | K25: =D25/C25 -> 0.042735043 | L25: =F25/E25 -> 0.9477155 | M25: =G25/E25 -> 0.89932407 | N25: =IF(C25<30,"too small to conclude",IF(OR(K25>$K$30+0.05,L25<$L$30-0.05),"risk",IF(OR(K25<$K$30-0.05,L25>$L$30+0.05),"strength","none"))) -> strength
A26: Medium (50-249) | B26: company_size | C26: 330 | D26: 34 | E26: 829786.84 | F26: 807264.26 | G26: 748682.86 | H26: 9792742.8 | I26: 12785193 | J26: =I26/H26-1 -> 0.3055784 | K26: =D26/C26 -> 0.1030303 | L26: =F26/E26 -> 0.97285739 | M26: =G26/E26 -> 0.90225926 | N26: =IF(C26<30,"too small to conclude",IF(OR(K26>$K$30+0.05,L26<$L$30-0.05),"risk",IF(OR(K26<$K$30-0.05,L26>$L$30+0.05),"strength","none"))) -> none
A27: Micro (1-9) | B27: company_size | C27: 353 | D27: 59 | E27: 364485.24 | F27: 338327.05 | G27: 308834.34 | H27: 4516903.8 | I27: 5678883.8 | J27: =I27/H27-1 -> 0.25725144 | K27: =D27/C27 -> 0.16713881 | L27: =F27/E27 -> 0.92823251 | M27: =G27/E27 -> 0.84731645 | N27: =IF(C27<30,"too small to conclude",IF(OR(K27>$K$30+0.05,L27<$L$30-0.05),"risk",IF(OR(K27<$K$30-0.05,L27>$L$30+0.05),"strength","none"))) -> none
A28: Small (10-49) | B28: company_size | C28: 543 | D28: 73 | E28: 795257.51 | F28: 760912.68 | G28: 695362.83 | H28: 9321205.2 | I28: 12761233 | J28: =I28/H28-1 -> 0.36905398 | K28: =D28/C28 -> 0.13443831 | L28: =F28/E28 -> 0.95681294 | M28: =G28/E28 -> 0.874387 | N28: =IF(C28<30,"too small to conclude",IF(OR(K28>$K$30+0.05,L28<$L$30-0.05),"risk",IF(OR(K28<$K$30-0.05,L28>$L$30+0.05),"strength","none"))) -> none
A30: Company (sum of the industry rows) | C30: =SUMIFS(C$7:C$28,$B$7:$B$28,"industry") -> 1343 | D30: =SUMIFS(D$7:D$28,$B$7:$B$28,"industry") -> 171 | E30: =SUMIFS(E$7:E$28,$B$7:$B$28,"industry") -> 3124736.3 | F30: =SUMIFS(F$7:F$28,$B$7:$B$28,"industry") -> 2982357 | G30: =SUMIFS(G$7:G$28,$B$7:$B$28,"industry") -> 2773798.8 | H30: =SUMIFS(H$7:H$28,$B$7:$B$28,"industry") -> 37258899 | I30: =SUMIFS(I$7:I$28,$B$7:$B$28,"industry") -> 45756419 | J30: =I30/H30-1 -> 0.22806688 | K30: =D30/C30 -> 0.12732688 | L30: =F30/E30 -> 0.95443477 | M30: =G30/E30 -> 0.88769051
A31: Check: region_group rows add up to the company total | C31: =AND(SUMIFS(C$7:C$28,$B$7:$B$28,"region_group")=C30,ABS(SUMIFS(I$7:I$28,$B$7:$B$28,"region_group")-I30)<0.01) -> TRUE
A32: Check: acquisition_channel rows add up to the company total | C32: =AND(SUMIFS(C$7:C$28,$B$7:$B$28,"acquisition_channel")=C30,ABS(SUMIFS(I$7:I$28,$B$7:$B$28,"acquisition_channel")-I30)<0.01) -> TRUE
A33: Check: company_size rows add up to the company total | C33: =AND(SUMIFS(C$7:C$28,$B$7:$B$28,"company_size")=C30,ABS(SUMIFS(I$7:I$28,$B$7:$B$28,"company_size")-I30)<0.01) -> TRUE
A34: Check: company 2025 revenue equals the 4a tab | C34: =ABS(I30-'4a Revenue quality'!F10)<0.01 -> TRUE

Sheet Q&A log
A1: Questions for management
A2: One row per question
A3: Source: docs/qa_log.md (qa_log table)
A5: ID | B5: Step | C5: Ref | D5: Topic | E5: Question | F5: Evidence | G5: Status
A6: Q01 | B6: Step 2 | C6: P07 | D6: Customer identity | E6: For each pair of customer_ids whose names differ only in "Ltd" against "Limited", are the two ids the same legal entity? If so, which id should revenue and contract history sit under? | F6: 229 pairs (458 customer_ids) share a normalised name. Within a pair, region, size, industry and account manager agree no more often than for random pairs, and most pairs run contracts at the same time. List in docs/data_profile.md section 12. | G6: open
A7: Q02 | B7: Step 2 | C7: P02 | D7: Other implementation revenue | E7: What work do the 2025 implementation invoices billed outside the customer's signup month relate to? Please provide the statement of work or contract for each. | F7: 45 invoices, £4,076,574 in total, ranging £32,292 to £147,347, all dated 2025, all for existing customers. Implementation invoices billed at signup have a median of £3,180. | G7: open
A8: Q03 | B8: Step 2 | C8: P02 | D8: Other implementation revenue | E8: What is the delivery and customer-acceptance status of each of these projects at December 2025? | F8: 3 of the 45 invoices (£277,704) are overdue. | G8: open
A9: Q04 | B9: Step 2 | C9: P02 | D9: Other implementation revenue | E9: On what basis is this revenue recognised: on invoice, on milestone, or on completion and acceptance? Is any of it deferred in the management accounts? | F9: £4,076,574 billed in 2025 on 45 invoices. | G9: open
A10: Q05 | B10: Step 2 | C10: P02 | D10: Other implementation revenue | E10: Are further projects of this kind contracted or expected in 2026? Please provide the pipeline with values and expected dates. | F10: None were billed in 2022 to 2024; all fall in 2025. | G10: open
A11: Q06 | B11: Step 2 | C11: P04 | D11: Duplicate invoices | E11: Were the duplicate invoice copies issued to customers, and are they included in the receivables ledger and the overdue balance? | F11: 40 exact duplicates removed, £96,957.26. Original and copy are both marked overdue in every case. | G11: open
A12: Q07 | B12: Step 2 | C12: P05 | D12: Management accounts | E12: In the months listed, the four product-line revenue figures do not add up to total revenue. Which figure is correct, and what caused the difference? | F12: 4 months: Jun 2023 +£18,500, Mar 2024 -£12,000, Nov 2024 +£9,500, Feb 2025 -£15,000. | G12: open
A13: Q08 | B13: Step 2 | C13: P06 | D13: Negative invoices | E13: What are the negative amounts on invoices marked paid? Are they credit notes recorded without the credit-note status, or sign errors? | F13: 15 invoices, -£13,843.82 in total. Each is the only billing for its customer, product and month; the months either side carry the same amount as a positive. | G13: open
A14: Q09 | B14: Step 2 | C14: P10 | D14: Contract dates | E14: What event does customers.signup_date record (contract signature, go-live or account creation)? Why are some first invoices dated before it? | F14: 1,423 invoices for 806 customers are dated 1 to 26 days before signup_date, always in the same calendar month. | G14: open
A15: Q10 | B15: Step 2 | C15: P08 | D15: Customer attributes | E15: Can management supply the industry for customers where it is blank? | F15: 132 customers have no industry; they are reported as Unknown. | G15: open
A16: Q11 | B16: Step 3 | C16: P06 | D16: Negative invoices | E16: Why were the negative amounts on invoices marked paid left out of reported revenue instead of being corrected? If they are sign errors, will the invoices and the management accounts be restated? | F16: 15 invoices. Reported revenue excludes them: the cube ties to the product lines in all 48 months only when they are excluded. The months either side of each carry the same amount as a positive, so reported revenue is probably understated by £13,843.82 (2022 £5,788.75, 2023 £2,118.96, 2024 £4,073.48, 2025 £1,862.63). | G16: open
... A26: Q21 | B26: Step 4 | C26: 4f | D26: Pricing | E26: What is the discount policy for large customers, who approves discounts, and are any discounts due to fall away or be renegotiated at renewal? | F26: Large customers average 22.2% off list; £5.35m given up across all customers in 2025. | G26: open

Sheet Checks
A1: Checks: every tie-out in the databook
A2: TRUE means the check passes
A3: Each row links to a check cell on another tab
A5: Overall check | C5: =AND(E8:E63) -> TRUE
A7: # | B7: Check | C7: Tab | D7: Cell | E7: Result
A8: 1 | B8: Reconciliation: cube ties to the management product lines in total | C8: Reconciliation | D8: I55 | E8: =Reconciliation!I55 -> TRUE
A9: 2 | B9: Reconciliation 2022: difference equals the documented unexplained items and the cube total ties to the pipeline | C9: Reconciliation | D9: I59 | E9: =Reconciliation!I59 -> TRUE
A10: 3 | B10: Reconciliation 2023: difference equals the documented unexplained items and the cube total ties to the pipeline | C10: Reconciliation | D10: I60 | E10: =Reconciliation!I60 -> TRUE
A11: 4 | B11: Reconciliation 2024: difference equals the documented unexplained items and the cube total ties to the pipeline | C11: Reconciliation | D11: I61 | E11: =Reconciliation!I61 -> TRUE
A12: 5 | B12: Reconciliation 2025: difference equals the documented unexplained items and the cube total ties to the pipeline | C12: Reconciliation | D12: I62 | E12: =Reconciliation!I62 -> TRUE
A13: 6 | B13: Walk 2022: cube net from the walk equals the annual reconciliation | C13: Reconciliation | D13: B74 | E13: =Reconciliation!B74 -> TRUE
A14: 7 | B14: Walk 2023: cube net from the walk equals the annual reconciliation | C14: Reconciliation | D14: C74 | E14: =Reconciliation!C74 -> TRUE
A15: 8 | B15: Walk 2024: cube net from the walk equals the annual reconciliation | C15: Reconciliation | D15: D74 | E15: =Reconciliation!D74 -> TRUE
A16: 9 | B16: Walk 2025: cube net from the walk equals the annual reconciliation | C16: Reconciliation | D16: E74 | E16: =Reconciliation!E74 -> TRUE
A17: 10 | B17: Reconciliation: every product line ties in every year | C17: Reconciliation | D17: F95 | E17: =Reconciliation!F95 -> TRUE
A18: 11 | B18: 4a 2022: net revenue ties to the Reconciliation tab | C18: 4a Revenue quality | D18: N7 | E18: ='4a Revenue quality'!N7 -> TRUE
A19: 12 | B19: 4a 2023: net revenue ties to the Reconciliation tab | C19: 4a Revenue quality | D19: N8 | E19: ='4a Revenue quality'!N8 -> TRUE
A20: 13 | B20: 4a 2024: net revenue ties to the Reconciliation tab | C20: 4a Revenue quality | D20: N9 | E20: ='4a Revenue quality'!N9 -> TRUE
A21: 14 | B21: 4a 2025: net revenue ties to the Reconciliation tab | C21: 4a Revenue quality | D21: N10 | E21: ='4a Revenue quality'!N10 -> TRUE
A22: 15 | B22: 4b 2022 top 1: total ties to 4a and share is between 0 and 100% | C22: 4b Concentration | D22: J7 | E22: ='4b Concentration'!J7 -> TRUE
A23: 16 | B23: 4b 2022 top 5: total ties to 4a and share is between 0 and 100% | C23: 4b Concentration | D23: J8 | E23: ='4b Concentration'!J8 -> TRUE
A24: 17 | B24: 4b 2022 top 10: total ties to 4a and share is between 0 and 100% | C24: 4b Concentration | D24: J9 | E24: ='4b Concentration'!J9 -> TRUE
A25: 18 | B25: 4b 2022 top 20: total ties to 4a and share is between 0 and 100% | C25: 4b Concentration | D25: J10 | E25: ='4b Concentration'!J10 -> TRUE
A26: 19 | B26: 4b 2023 top 1: total ties to 4a and share is between 0 and 100% | C26: 4b Concentration | D26: J11 | E26: ='4b Concentration'!J11 -> TRUE
A27: 20 | B27: 4b 2023 top 5: total ties to 4a and share is between 0 and 100% | C27: 4b Concentration | D27: J12 | E27: ='4b Concentration'!J12 -> TRUE
A28: 21 | B28: 4b 2023 top 10: total ties to 4a and share is between 0 and 100% | C28: 4b Concentration | D28: J13 | E28: ='4b Concentration'!J13 -> TRUE
A29: 22 | B29: 4b 2023 top 20: total ties to 4a and share is between 0 and 100% | C29: 4b Concentration | D29: J14 | E29: ='4b Concentration'!J14 -> TRUE
A30: 23 | B30: 4b 2024 top 1: total ties to 4a and share is between 0 and 100% | C30: 4b Concentration | D30: J15 | E30: ='4b Concentration'!J15 -> TRUE
A31: 24 | B31: 4b 2024 top 5: total ties to 4a and share is between 0 and 100% | C31: 4b Concentration | D31: J16 | E31: ='4b Concentration'!J16 -> TRUE
A32: 25 | B32: 4b 2024 top 10: total ties to 4a and share is between 0 and 100% | C32: 4b Concentration | D32: J17 | E32: ='4b Concentration'!J17 -> TRUE
A33: 26 | B33: 4b 2024 top 20: total ties to 4a and share is between 0 and 100% | C33: 4b Concentration | D33: J18 | E33: ='4b Concentration'!J18 -> TRUE
... A37: 30 | B37: 4b 2025 top 20: total ties to 4a and share is between 0 and 100% | C37: 4b Concentration | D37: J22 | E37: ='4b Concentration'!J22 -> TRUE
A38: 31 | B38: 4d 2023: opening MRR ties to the 4a ARR | C38: 4d NRR GRR | D38: B20 | E38: ='4d NRR GRR'!B20 -> TRUE
A39: 32 | B39: 4d 2024: opening MRR ties to the 4a ARR | C39: 4d NRR GRR | D39: C20 | E39: ='4d NRR GRR'!C20 -> TRUE
A40: 33 | B40: 4d 2025: opening MRR ties to the 4a ARR | C40: 4d NRR GRR | D40: D20 | E40: ='4d NRR GRR'!D20 -> TRUE
A41: 34 | B41: 4d NRR: SMB benchmark range recomputed from benchmarks.csv equals the 4d notebook | C41: 4d NRR GRR | D41: I60 | E41: ='4d NRR GRR'!I60 -> TRUE
A42: 35 | B42: 4d NRR before price increase: SMB benchmark range recomputed from benchmarks.csv equals the 4d notebook | C42: 4d NRR GRR | D42: I61 | E42: ='4d NRR GRR'!I61 -> TRUE
A43: 36 | B43: 4d GRR: SMB benchmark range recomputed from benchmarks.csv equals the 4d notebook | C43: 4d NRR GRR | D43: I62 | E43: ='4d NRR GRR'!I62 -> TRUE
A44: 37 | B44: 4e ARR bridge 2023: opening plus components equals closing ARR from the cube | C44: 4e ARR bridge | D44: B17 | E44: ='4e ARR bridge'!B17 -> TRUE
A45: 38 | B45: 4e ARR bridge 2024: opening plus components equals closing ARR from the cube | C45: 4e ARR bridge | D45: C17 | E45: ='4e ARR bridge'!C17 -> TRUE
A46: 39 | B46: 4e ARR bridge 2025: opening plus components equals closing ARR from the cube | C46: 4e ARR bridge | D46: D17 | E46: ='4e ARR bridge'!D17 -> TRUE
A47: 40 | B47: 4e revenue bridge 2023: components add up to net revenue | C47: 4e ARR bridge | D47: B49 | E47: ='4e ARR bridge'!B49 -> TRUE
A48: 41 | B48: 4e revenue bridge 2024: components add up to net revenue | C48: 4e ARR bridge | D48: C49 | E48: ='4e ARR bridge'!C49 -> TRUE
A49: 42 | B49: 4e revenue bridge 2025: components add up to net revenue | C49: 4e ARR bridge | D49: D49 | E49: ='4e ARR bridge'!D49 -> TRUE
A50: 43 | B50: 4f 2023: mix plus rate equals the change in blended margin | C50: 4f Margin | D50: C47 | E50: ='4f Margin'!C47 -> TRUE
A51: 44 | B51: 4f 2024: mix plus rate equals the change in blended margin | C51: 4f Margin | D51: D47 | E51: ='4f Margin'!D47 -> TRUE
A52: 45 | B52: 4f 2025: mix plus rate equals the change in blended margin | C52: 4f Margin | D52: E47 | E52: ='4f Margin'!E47 -> TRUE
A53: 46 | B53: 4f 2022: gross profit ties to management apart from the unexplained revenue adjustments; costs tie | C53: 4f Margin | D53: B56 | E53: ='4f Margin'!B56 -> TRUE
A54: 47 | B54: 4f 2023: gross profit ties to management apart from the unexplained revenue adjustments; costs tie | C54: 4f Margin | D54: C56 | E54: ='4f Margin'!C56 -> TRUE
A55: 48 | B55: 4f 2024: gross profit ties to management apart from the unexplained revenue adjustments; costs tie | C55: 4f Margin | D55: D56 | E55: ='4f Margin'!D56 -> TRUE
A56: 49 | B56: 4f 2025: gross profit ties to management apart from the unexplained revenue adjustments; costs tie | C56: 4f Margin | D56: E56 | E56: ='4f Margin'!E56 -> TRUE
A57: 50 | B57: 4f 2025: discount by size band adds up to the annual total | C57: 4f Margin | D57: E72 | E57: ='4f Margin'!E72 -> TRUE
A58: 51 | B58: 4f 2025: size-band revenue and allocated cost add back to the totals (within 5p of rounding) | C58: 4f Margin | D58: D80 | E58: ='4f Margin'!D80 -> TRUE
A59: 52 | B59: 4g: region_group segments add up to the company totals | C59: 4g Segments | D59: C31 | E59: ='4g Segments'!C31 -> TRUE
A60: 53 | B60: 4g: acquisition_channel segments add up to the company totals | C60: 4g Segments | D60: C32 | E60: ='4g Segments'!C32 -> TRUE
A61: 54 | B61: 4g: company_size segments add up to the company totals | C61: 4g Segments | D61: C33 | E61: ='4g Segments'!C33 -> TRUE
A62: 55 | B62: 4g: company 2025 revenue ties to 4a | C62: 4g Segments | D62: C34 | E62: ='4g Segments'!C34 -> TRUE
A63: 56 | B63: Basis: raw invoices plus cleaning adjustments equal the cube net revenue | C63: Basis | D63: F27 | E63: =Basis!F27 -> TRUE
